{"songs": [{"title": "Or Noir (Remix)", "album": null, "year": null, "lyrics": "[Couplet 1]\nJe regrette d'\u00eatre partie\nDakar S\u00e9n\u00e9gal ma patrie\nJ'oublie pas les souvenirs\nQuand j'y pense j'me fais souffrir\nJe ne pleure plus je rap\nJe ne dors plus la night\nBerc\u00e9e par le bruit des balles\nJ'aime ma miff comme une rital\nTu m'as vu marcher l'coeur ouvert\nMontrer au monde mes blessures, mes plaies\nJ'crois en Dieu c'est mon seul rep\u00e8re\nMa m\u00e8re c'est la meilleure des m\u00e8res\nDur comme fer, j'suis noire comme l'\u00e9b\u00e8ne\nJ'ai tout fait pour enlever mes cha\u00eenes\nKainfry jusque dans mes veines\nPoulet frit maf\u00e9 tchiep bou dieune\nT\u00e9ma, mes lossa\nComptent sur moi\nBande de tar-ba\nIl n'y aura pas de rot-ca\nSeule la mort nous emportera\nJ'vais tout rafler j'veux l'or noir ou jaune\nQuitt\u00e9 \u00e0 y laisser ma peau\nNe me juge pas, tu ne sais pas\nPour qui ou pour quoi je m\u00e8ne ma cause\n\n[Refrain]\nCar je n'ai que ma famille\nPas d'amis\nMes ennemis\nEt cette m\u00e9lodie\nMoi je n'ai que ma famille pas d' amis\nDans cette chienne de vie\nDes ennuis, des ennemis\nEt cette m\u00e9lodie\n\n[Couplet 2]\nEntre le bitume et la plage\nY a que le sable qui nous s\u00e9pare\nJ'ferai des choses ill\u00e9gales\nSi la musique ne marche pas\nJ'suis trop d\u00e9ter v\u00e9n\u00e8r \u00e0 l'\u00e8re o\u00f9\nTous les boloss veulent de l'oseille\nBelek si tu cherches les miens tu m'trouves\nAppelle les chiens, tu tombes sur une louve\nPas de chargeur sans l'remplir de ye-dou\nL'industrie nous a bien cass\u00e9 les ye-cou\nPourquoi j'voudrais rentrer dans votre moule\nY a plus de r\u00e8gles quand j'vois tout en rouge\nJ'ai ouvert mon coeur et pas la bouteille\n\u00c0 part mes darons j'veux pas de tes conseils\nToujours en noir\nToujours en deuil\nToujours en retard\nToujours \u00e0 l'heure\nM\u00eame dans la merde on reste vrai\nPeur de personne touche pas \u00e0 mes r\u00eaves\nGrosse Qualit\u00e9, carats\nMa fiert\u00e9 est rang\u00e9e dans le cartable\nMa couleur passe la nuit en gardav\nMais ne sait pas que j'leur r\u00e9serve du sale\n\n[Refrain x2]", "image": "https://images.genius.com/a7a2e0afd5530418dfe636985e59712c.691x691x1.jpg"}], "artist": "Sarahme\u0301e"}