{"songs": [{"title": "\u00c9l\u00e9phant", "album": "La Nuit des Longs Couteaux", "year": "2018-05-18", "lyrics": "[1er couplet]\nL\u2019impression que mes journ\u00e9es sont sans lendemain\nTout le monde essaie d'entrer dans mon brain\nJ\u2019ai ferm\u00e9 les blinds, j\u2019ai ouvert le mind\nRestart\u00e9 le grind pour me prendre en mains\nFaut que j\u2019m\u2019arr\u00eate pour refaire le plein\nFinie la guerre, l\u00e0 j\u2019desserre les poings\nMon cerveau d\u00e9raille mais l\u00e0 c\u2019est mon time\nJ\u2019s\u00e8me la pagaille si j\u2019manque le train\nLe r\u00e9pondeur de mon cell est vide\nJ\u2019veux compter les heures mais j\u2019en perd le fil\nJ\u2019ai s\u00e9ch\u00e9 les pleurs, j\u2019ai ferm\u00e9 mon c\u0153ur, j\u2019ai fait des longueurs dans mon verre de gin\nJ\u2019entends les \u00e9chos des gens qui scandent des demandes que leur h\u00e9ros vienne fendre le vent\nY\u2019a pas de tr\u00f4ne, de King ou de messie\nY\u2019a seulement des egos qui se rentrent dedans\nJ\u2019ai compt\u00e9 le cash, fait tomber le match\nJ\u2019ai brul\u00e9 la cape et le costume\nJ\u2019pas plus catholique que le pape\nMoi j\u2019veux les m\u00e9dailles, le cash et la fortune\nY\u2019a longtemps que j\u2019ai vendu mon c\u0153ur\nJ\u2019peux m\u00eame plus sentir la peur\nSi j\u2019reviens \u00e0 100 milles \u00e0 l\u2019heure\nTu sais que c\u2019est pour remettre les pendules \u00e0 l\u2019heure\nJ\u2019ai tu\u00e9 les miens comme un meurtrier\nLanc\u00e9 des amis aux oubliettes\nLe jour ou la nuit, j\u2019sais pas l\u2019heure qu\u2019il est\nJ\u2019veux revenir en arri\u00e8re \u00e0 toute vitesse\nC\u2019tait pas dans mes plans de berner des gens\nDe tout sauter en allumant la m\u00e8che\nJ\u2019prends le couteau qu\u2019on m'a plant\u00e9 dans le dos pour tuer l\u2019\u00e9l\u00e9phant que je vois dans la pi\u00e8ce\n\n[Refrain]\nLeave me alone\nLaissez-moi seul dans ma zone\nFermer les stores et j\u2019ai ferm\u00e9 le phone\nJ\u2019ai pas la force d\u2019aller r\u00e9gler des comptes, de r\u00e9parer des ponts\nNah, leave me alone\nLaissez-moi dans les d\u00e9combres\nLaissez-moi dont seul pour creuser ma tombe\nLaissez-moi pr\u00e9parer la fin du monde\nJ\u2019ai dit leave me alone\nAye, Leave me alone\nLaissez-moi seul dans ma zone\nFermer les stores et j\u2019ai ferm\u00e9 le phone\nJ\u2019ai pas la force d\u2019aller r\u00e9gler des comptes, de r\u00e9parer des ponts\nNah, leave me alone\nLaissez-moi dans les d\u00e9combres\nLaissez-moi dont seul pour creuser ma tombe\nLaissez-moi pr\u00e9parer la fin du monde\nJ\u2019ai dit leave me alone\n\n[2\u00e8me couplet]\nMes journ\u00e9es sont sans lendemain\nTout le monde essaie d'entrer dans mon brain\nJ\u2019ai r\u00e9gler les drames, j\u2019ai s\u00e9ch\u00e9 les larmes\nJ\u2019ai jet\u00e9 les armes pour me rendre enfin\nLever les voiles d\u00e9laissant mes kids\nTrouver les \u00e9toiles en plein centre-ville\nMais j\u2019ai mis les brakes, rep\u00e9r\u00e9 les snakes avant que les amiti\u00e9s s\u2019enveniment\nMa vie, j\u2019la d\u00e9crit pis j\u2019l\u2019enregistre\nMon histoire est \u00e9crite \u00e0 l\u2019encre de Chine\n\u00c9checs et victoires, c\u2019que dans mon miroir\nJ\u2019l\u2019\u00e9cris pour compenser le manque d\u2019estime\nJ\u2019me fait engag\u00e9 pour faire du bruit\nMoney qui rentre pour les droits d\u2019auteurs\nRien \u00e0 donner pour les ennemis\nQue mon silence et mes doigts d\u2019honneur\nAmph\u00e9tamines pour me concentrer\nJ\u2019fais d\u2019la vitesse sous les yeux d\u2019la peur\n\u00c0 force d\u2019emmerder le monde entier\nJ\u2019ai des biceps sur mes deux majeurs\nJ\u2019ai des amis qui veulent pu me revoir depuis que j\u2019ai trouv\u00e9 le bonheur dans mon compte ch\u00e8que\nJ\u2019ai trouv\u00e9 dieu dans un urinoir\nJ\u2019ai laiss\u00e9 mon honneur au coat check\nRempli mon sac, j\u2019suis parti la nuit\nTrahi notre amour dans tous mes gestes\nJ\u2019ai voulu partir et fuir ma vie\nJ\u2019veux revenir en arri\u00e8re \u00e0 toute vitesse\n\u00catre un tyran, c\u2019\u00e9tait pas dans mes plans\nNon, jamais j\u2019ai fak\u00e9 la gentillesse\nJ\u2019prends le couteau que je t'ai plant\u00e9 dans le dos pour tuer l\u2019\u00e9l\u00e9phant que je vois dans la pi\u00e8ce\n\n[Refrain]\nLeave me alone\nLaissez-moi seul dans ma zone\nFermer les stores et j\u2019ai ferm\u00e9 le phone\nJ\u2019ai pas la force d\u2019aller r\u00e9gler des comptes, de r\u00e9parer des ponts\nNah, leave me alone\nLaissez-moi dans les d\u00e9combres\nLaissez-moi dont seul pour creuser ma tombe\nLaissez-moi pr\u00e9parer la fin du monde\nJ\u2019ai dit leave me alone\nAye, Leave me alone\nLaissez-moi seul dans ma zone\nFermer les stores et j\u2019ai ferm\u00e9 le phone\nJ\u2019ai pas la force d\u2019aller r\u00e9gler des comptes, de r\u00e9parer des ponts\nNah, leave me alone\nLaissez-moi dans les d\u00e9combres\nLaissez-moi dont seul pour creuser ma tombe\nLaissez-moi pr\u00e9parer la fin du monde\nJ\u2019ai dit leave me alone\n\n\n[3\u00e8me couplet]\nYa\nL\u2019impression que mes journ\u00e9es sont sans lendemain\nTout le monde essaie d'entrer dans mon brain\nJ\u2019ai baiss\u00e9 mes gardes, d\u00e9m\u00eal\u00e9 les cartes, so l\u00e8ve ta main droite si tu m\u2019entends bien\nJ\u2019fais chanter les gens pour gagner ma vie, mais j\u2019ai fr\u00e9quent\u00e9 l\u2019envie de m\u2019enlever la vie\nJ\u2019fais des confessions devant des \u00e9trangers\nJ\u2019rentre sur un beat comme en th\u00e9rapie\nJ\u2019ai rempli mon assiette en dessous de la table\nLaiss\u00e9 du sang sur mon couteau de chasse\nFerm\u00e9 les oreilles \u00e0 vos conseils\nLa seule voix qui me guide, c\u2019est Google Map\nLa vie publique, c\u2019est bittersweet\nParti sans vous donner signe de vie\n\u00c0 la recherche de mon inner peace\nJ\u2019l\u2019ai pas trouv\u00e9 sur mon Twitter feed\nJ\u2019ai err\u00e9 nulle part, j\u2019ai perdu le nord\nJ\u2019ai dormi dehors sous la pleine lune\nMis tous les efforts pour avouer mes torts\nMais j\u2019ai saoul\u00e9 mon corps dans l\u2019amertume\nJ\u2019ai manqu\u00e9 d\u2019air dans mes crises de nerfs\nFait sauter ma t\u00eate dans la d\u00e9pression\nJ\u2019ai fait un r\u00eave o\u00f9 j\u2019poignardais mon p\u00e8re\nJ\u2019me suis r\u00e9veill\u00e9 en \u00e9rection\nJ\u2019ai tu\u00e9 mon nom comme un meurtrier\nLanc\u00e9 mon avenir aux oubliettes\nJ\u2019ai mis du tape sur mon c\u0153ur bris\u00e9\nJ\u2019veux revenir en arri\u00e8re \u00e0 toute vitesse\nC\u2019tait pas dans mes plans de ruiner ton temps, d\u2019arracher ton c\u0153ur comme une dent de sagesse\nJ\u2019prends le couteau que je t'ai plant\u00e9 dans le dos pour tuer l\u2019\u00e9l\u00e9phant que je vois dans la pi\u00e8ce\n\n[Refrain]\nLeave me alone\nLaissez-moi seul dans ma zone\nFermer les stores et j\u2019ai ferm\u00e9 le phone\nJ\u2019ai pas la force d\u2019aller r\u00e9gler des comptes, de r\u00e9parer des ponts\nNah, leave me alone\nLaissez-moi dans les d\u00e9combres\nLaissez-moi dont seul pour creuser ma tombe\nLaissez-moi pr\u00e9parer la fin du monde\nJ\u2019ai dit leave me alone\nAye, Leave me alone\nLaissez-moi seul dans ma zone\nFermer les stores et j\u2019ai ferm\u00e9 le phone\nJ\u2019ai pas la force d\u2019aller r\u00e9gler des comptes, de r\u00e9parer des ponts\nNah, leave me alone\nLaissez-moi dans les d\u00e9combres\nLaissez-moi dont seul pour creuser ma tombe\nLaisser moi pr\u00e9parer la fin du monde\nJ\u2019ai dit leave me alone", "image": "https://images.genius.com/1ecfd278d718ff7f57878a1e62ad8bb0.200x200x1.jpg"}], "artist": "Koriass"}