{"songs": [{"title": "Plus Haut", "album": "Plus Haut", "year": "2016-09-13", "lyrics": "[Verse 1]\n\nJ'ai la t\u00eate dans les nuages\nJ'ai le coeur sous la main\nJ'veux le sable d'une plage\nDe l'amour sans fin\nJ'ai le pied dansant\nLa musique dans l\u2019\u00e2me\nJ'ai le beat dans le sang\nOn va chanter ensemble\nOn va sculpter notre avenir\nDans les consones et voyelles\nOn va se donner des fous rires\nOn va se donner des ailes\nOn va allez plus haut\nSe faire la courte \u00e9chelle\nOn va allez plus haut\nLa limite c'est le ciel\n\n[Chorus 1]\n\nOn va allez plus haut\nLa musique dans l\u2019\u00e2me\nOn va allez plus haut\nOn va chantez ensemble\n\n[Verse 2]\n\nLe monde c'est mon canevas\nJ'met de la couleur comme un peintre sur un tableau\n(Un peintre sur un tableau)\nJ'aime jouer avec les lettres & les mots sur la page comme les touches sur un piano\n(Les touches sur un piano)\nLe ciel c'est ma limite, j'fais danser les notes et ma fus\u00e9e d\u00e9colle\n(D\u00e9colle)\nJ'fais glisser ma plume, j'fais vibrer les cordes\nLa musique me sculpte et l'\u00e9corce\nJ'vole dans les airs vers le soleil\nJ'vie dans mes r\u00eaves mais pas juste quand j'ai sommeil\nJ'deviens un prince, un peintre, un po\u00e8te\nJ'vois l'univers \u00e0 cheval sur une com\u00e8te\nJ' veux aller plus haut, danser sur la lune\nAllez jusqu'au anneaux d'la plan\u00e8te Saturne\nJ'avance dans la nuit pis j'peux voir dans la brume\nJ'regarde les \u00e9toiles et je sais que j'en suis une\n\n\n[Chorus 2]\n\nOn va allez plus haut\nLa musique dans l\u2019\u00e2me\nOn va allez plus haut\nOn va chantez ensemble", "image": "https://images.genius.com/a5fea99b11ac3a21a7b9ce9be06f90d3.700x700x1.jpg"}], "artist": "Koriass"}