{"songs": [{"title": "New Phone Interlude", "album": "New Phone", "year": "2017-04-27", "lyrics": "Yeah, yeah\nJe sais, j'\u00e9tais juste un musicien parmi tant d'autres\nPis t'\u00e9tais juste une muse, mais c't'assez pour un tango\nComme des poissons dans l'eau quand on allait down low\nManteaux d'arm\u00e9e assortis, on peut sortir commando\nBreak up in a sec sans m\u00eame break a sweat\nWake up, caf\u00e9 \u00e9cossais, make up sex\nNos humeurs changeaient comme notre trame sonore\nIpod en mode shuffle\nBone Thugs-N-Harmonium\nA Beach house by the Frank Ocean\nNos esprits d\u00e9rivent pendant que les joints se consument\nBinge fucking and chain smoking\nJ'fais pu de drogues de m\u00eame ces jours-ci\nC'est pu comme avant\nJ'avais les r\u00eaves de visionnaire\nJ'faisais les cauchemars d'une vie honn\u00eate\nTu m'as dit: \u00abtu peux pas rester pour me voir foutre ma vie en l'air\u00bb\nBut I told you we would be alright, right\nI guess t'as raccroch\u00e9 trop vite\nMaintenant tu m'appelles sur mon new phone\nLooking for the old me\nMaintenant tu m'appelles sur mon new phone\nLooking for the old me\nMaintenant que t'as compris que j'ai move on\nC'est l\u00e0 que t'essayes de mettre tes moves on me\nMaintenant tu m'appelles sur mon new phone\nLooking for the old me\nMais tu vas chercher longtemps", "image": "https://images.genius.com/0f0135aa35a853592910cbe643750519.960x960x1.jpg"}], "artist": "Loud (Canada)"}