{"songs": [{"title": "Un Bras d'Distance", "album": "G.O.L.F. : Gangster Original De La Langue Fran\u00e7aise", "year": "2015-08-20", "lyrics": "[Intro]\n\nUn bras d'distance x8\n\n[Refrain]\n\nNous on s'en criss de c'est quoi tu pense\nY ont aduler mes flatulence\nQuatre-cent-cinquante-mille dans l\u2019assistance\nBig t'es mieux d'appeler une ambulance\nQuan-Quan-quand qu'a m'parle (un bras d'distance)\nQuan-Quan-quand qu'a m'suce (un bras d'distance)\nQuan-Quan-quand qu'a m'parle (un bras d'distance)\nQuan-Quan-quand qu'a m'suce (un bras d'distance)\n\n[Verse]\n\nUn pick-up rempli d'poudre, ch'tais sur l'autoroute\nAvec Mr. Mitof\u00e9 big j'suis rendu c'est cot\u00e9s\n44 a mes cot\u00e9s, Ford F-5-50\n[?], a un bras d'distance (un bras d'distance)\nUn p'tit tripe a Tadousac, y'er dev'nu millionnaire\nDes lignes sur l'autoroute long comme des kilom\u00e8tres\nDemande a Matador c'est qui qui op\u00e8re (R\u00e9gis)\nLe gros fait dont d'l'espaces, Biosph\u00e8re\nUn bras d'distance quand j'commande une escorte je compose le 9-1-1 envois moi dont une femme qu'y'er faite forte\nJ'ai acheter une limousine anti-pala avec 7 portes\nArr\u00eate de payer ta drogue trop ch\u00e8re, big on exporte\nSituation financi\u00e8re, magnifique\nA cot\u00e9 d'Sir Path\u00e9tique on a tous l'aire athl\u00e9tique\nLe gros sa bitch m'as demander d'y frapper l'vagin\nMais s't'une criss de folle faque j'l'ai garder a\n\n[Riff]\n\nUn bras d'distance x8\n\nNous on s'en criss de c'est quoi tu pense\nY ont aduler mes flatulence\nQuatre-cent-cinquante-mille dans l\u2019assistance\nBig t'es mieux d'appeler une ambulance\nQuan-Quan-quand qu'a m'parle (un bras d'distance)\nQuan-Quan-quand qu'a m'suce (un bras d'distance)\nQuan-Quan-quand qu'a m'parle (un bras d'distance)\nQuan-Quan-quand qu'a m'suce (un bras d'distance)\n\n[Verse]\n\nJ'avais 7 ans la premi\u00e8re fois que j'ai bu d'l\u00e9taire\nJ'avais 6 tonne de poudre dans le nucl\u00e9aire\nJ'suis un thug, J'viole tes soeur pis je tue t'es fr\u00e8res\nM'redis moi pas \u00e0 ouvrir un salon fun\u00e9raire\nTa fiancer m'a check, elle enleve son alliance\nElle veut pas un fife qui vas au coll\u00e8ge Marie-d'france\nTabarnak de snitch faut arr\u00eater tes manigances\nOn est omnipr\u00e9sent on a d\u00e9fier la distance\nJ'fais des marathons pis du karat\u00e9\nShout moi des bullets de Baretta j'vas t'l'ai attraper\nQuand j'fourrais ta bitch elle m'as d'mander d'la taper\nLe gros gr\u00e2ce \u00e0 mon sperme elle sait comment envaler\nSi elle \u00e0 la bouge plein, elle pourra pas parler\nM\u00eame quand elle me suce pas le queue elle a pas l'droit de parler\nJ'l'ai fait griller la premi\u00e8re fois qu'elle m'a regarder\nTu sais comment faire bitch oublie pas de garder un\n\n[Riff]\n\nUn bras d'distance x8\n\n[Verse]\n\nJ'garde le bar \u00e0 Plotte, \u00e0 un bras d'distance\nUne paire de tonton, \u00e0 un bras d'distance\nFuck la police, un bras d'distance\nMon pack de sesh est \u00e0 un bras d'distance\nUne 28 de l'aurentide \u00e0 un bras d'distance\nMes conif\u00e8re, un bras d'distance\nTu pu d'la yeule, un bras d'distance\nT'es n\u00e9e \u00e0 Longeuil ? un bras d'distance\nDes condoms magnum s't'un bras d'distance\nUn barreaux d'chaise long, comme un bras d'distance", "image": "https://images.genius.com/dc79b699d4f5f1e6c74b6f5734126358.500x500x1.jpg"}], "artist": "Les Anticipateurs"}