{"songs": [{"title": "3\u00e8me p\u00e9riode", "album": "Tour Du Chapeau", "year": "2012-11-21", "lyrics": "[Intro: MC Tronel + La Belle Province St-Cath/Main]\nMa prendre eh un trio eh num\u00e9ro 2 s.t.p\n8.60$, avec tip, 8.60$\nToasters, une frite, toasters une frite\n\n[Chorus: MC Tronel]\nOn est number one au Qu\u00e9bec\nJuste des wins z\u00e9ro d\u00e9faites\nOn sait pas comment perde\nOn sait juste comment gagn\u00e9\nBig la poud, t'en a dans'l nez\n\nAnticipateurs, c'est nous les best (Anticipateurs)\nBig, le game y'est en d\u00e9tresse\nFaque nous \u00f4tes on va'l sauver\nPis ton spliff on va'l doser\nJean-R\u00e9gis y va t'coacher\n\n[Verse 1: MC Tronel]\nLes Anticipateurs en sup\u00e9riorit\u00e9 num\u00e9rique (ouin)\nTa bitch a le go\u00fbt de nous sucer le dick depuis qu'a l'a vu les clips (aweille suce)\nAstheure, t'as perdu toute ta famille pis t'as pu d'\u00e9quipe (sac de couchage)\nCocktail molotov quand qu'on tue des chicks (ouin)\n\nAssasinateurs (k), assa' assasinateurs (k)\nJ'ai mis Josiane pis sa s\u0153ur dans un incin\u00e9rateur\nJ'ai un calumet d'la paix, pis un chalumeau d'l'Enfer (yes)\nJ'fume un buzz, j'veux un suit, j'demande \u00e0 Hugo d'm'en faire, HOMME DE FER (PLATINE)\n\nJ'fais d'la soudure pour les Aciers Richelieu\nWhisky au sirop d'\u00e9rable, on est paquet\u00e9, oui monsieur\nJ'suis buzzer en motadine, le gros d\u00e9compose ma rime\nDu silicone dans les seins, a suce ben avec ses fausses babines\n\n(Go Pauline) Nous \u00f4tes, on aime piloter des grosses machines\nProduction trop efficace comme si on contr\u00f4le la Chine\n(Jean-R\u00e9gis) Meilleur produceur de toute l'Humanit\u00e9\nJ'suis fatigu\u00e9, pour m'r\u00e9veill\u00e9 y faut que j'vois des culs agit\u00e9s (crisse)\n\nBouge des fesses, faut tu bouges tes fesses (yes), tu sais qu'c'est nous les bests (ouin)\nFaits ton Saint, aweille fait ton Saint, j'ai les ballons pleins (ouin)\nTouche ta noune (crisse), faut tu touches ta noune (crisse), quand qu'on joue ta toune (ouin)\nOuvre la bouche, frotte tes cuisses, bitch si tu veux pas d\u00e9crisse (d\u00e9crisse)\n\n[Hook: MC Tronel]\nElle aime \u00e7a dans la passe (c't'un tour du chapeau)\nQuand qu'on patine s'a glace (c't'un tour du chapeau)\nQuand qu'on a la puck, on score (un tour du chapeau)\nCrisse osti qu'les gars sont forts (un tour du chapeau)\n\n[Verse 2: MC Monak]\n(Monak)\nLe gros, on devenu des pros sur la patinoire (la patinoire)\nAdditionne toutes les statistiques, c'est rien qu'des victoires (yes)\nAstheure, t'as perdu toute ton cash, pis ta femme aussi (crisse)\nElle aime \u00e7a dans face quand qu'elle s'essuie (Zamboni)\n\nFlow ventilateur, flow ven' flow ventilateur (ouin)\nLe gros quand j'\u00e9coute du Gilles Vigneault dans l'amplificateur\nC'est comme faire 3-4 peanuts aux Festival de la Gibelotte (ouin)\nBig, j'ai tellement de sac Ziploc, j'ai \u00f4t\u00e9 l'Gyproc du pick-up\n\n(Go) J'ai grandi dans du Jean Guy pis quand j'ach\u00e8te, j'invente le prix\nScore des buts apr\u00e8s la game, m'enva descendre une pente (go) de ski\n9 \u00e0 5 sur le corner du lundi au vendredi (yes)\nSamedi pis dimanche aussi on vends d'la patente en esti (ouin)\n\nAu Qu\u00e9bec, on anticipe, big c'est profond dans la joute\n(J't'e parle pas des s\u00e9ries) Quand qu'j't'e dis qu'\u00e7a sent la coupe (pantoute)\nNous \u00f4tes on est sapoud, on s'en calice comment \u00e7a co\u00fbte\nJ'y ai dit: \u00ab T'as pu d'place \u00bb\nElle m'a dit : \u00ab Big, rente la toute \u00bb\n\nTourne to\u00e9 d'bord (yes), aweille tourne to\u00e9 d'bord (yes), rien qu'des bruns \u00e0 soir (yes) (ouin)\nJ'y va fort, j'y va tellement fort (ouin), tu peux pu d'asseoir (ouin)\nSuce mon gland (yes), aweille suce mon gland (crisse), j'va d'\u00eatre plus content (ouin)\nOuvre tes jambes, pas ta bouche, l\u00e0 t'as l'impression qu't'accouche (ahh crisse)\n\n[Hook]\n\n[Chorus]", "image": "https://images.genius.com/33ab8babfd3f1d720629099047a8bc55.420x420x1.jpg"}], "artist": "Les Anticipateurs"}