{"songs": [{"title": "Je Me Souviens", "album": "Mar\u00e9e Humaine", "year": "2012-09-11", "lyrics": "[Verse 1]\nOn met l\u2019cap sur un r\u00eave mais la travers\u00e9e est longue\nCombien tr\u00e9passent avant d\u2019toucher l\u2019nouveau monde\nOn est Breton, Normand, Irlandais\nOu peu importe, on s\u2019m\u00e9lange esp\u00e9rant vivre en paix\n\nGrand- maman dit m\u00eame qu\u2019on a du sang am\u00e9rindien\nJ\u2019me demande si on n\u2019a plus dans nos veines ou sur nos mains\nOn fait une guerre, on la perd, j\u2019me sens trahi\nComme un flo rejet\u00e9 par sa M\u00e8re patrie\n\nMes nouveaux ma\u00eetres m\u2019exploitent, j\u2019commence \u00e0 \u00eatre \u00e9coeur\u00e9\nJ\u2019m\u2019en remets \u00e0 Dieu mais entre nous deux ya monsieur l\u2019cur\u00e9\nChaque jour j\u2019laboure une terre qui m\u2019appartenait\nChaque nuit j\u2019r\u00eave de violer leurs accords de paix\n\nMa fiert\u00e9 est \u00e0 poil et des mains sales la tripotent\nJ\u2019prends les armes en rejoignant les patriotes\nMais pendant qu\u2019on pend mes chefs au Pied du Courant\nMa maison br\u00fble sur les rives d\u2019un Richelieu rouge sang\n\n[Refrain]\nOn m\u2019a vol\u00e9 ma victoire\nCrach\u00e9 sur c\u2019que j\u2019avais d\u2019histoire\nMais j\u2019me souviens d\u2019o\u00f9 j\u2019viens\nPourquoi jamais j\u2019me suis battu pour rien\nParce qu\u2019on m\u2019a vol\u00e9 ma victoire\nCrach\u00e9 sur c\u2019que j\u2019avais d\u2019histoire\nMais j\u2019me souviens d\u2019o\u00f9 j\u2019viens\nJe me souviens\n\nJ\u2019voudrais grimper la montagne mais y\u2019en a pas d\u2019facile\nQuand ta langue t\u2019emp\u00eache de sortir du bas d\u2019la ville\nFaique j\u2019me barre le dos dans leurs vielles usines\nEt la reine r\u00e9colte le miel que les queb butinent\n\nMoi j\u2019mets la table, chu remerci\u00e9 qu\u2019par des miettes\nJ\u2019prends des balles pour leur empire sur les plages de Dieppe\nQuand qu\u2019une voix mondiale s\u2019l\u00e8ve comme un souffle d\u2019apr\u00e8s-guerre\nElle dit qu\u2019elle veut sa libert\u00e9 pis qu\u2019aucune arme la ferait taire\n\nSur toute la terre, les rebelles montent le ton\nMais plus les id\u00e9es sont belles moins les m\u00e9thodes le sont\nMoi j\u2019reste tranquille mais pense pas que j\u2019ferme ma trappe\nJ\u2019manifeste tremp\u00e9 jusqu\u2019aux os sous une pluie d\u2019matraques\n\nJ\u2019gagne du terrain j\u2019ai p\u2019t\u2019\u00eatre pas toutes mes droits\nMais j\u2019peux presque sentir mon r\u00eave au bout d\u2019mes doigts\nOn m\u2019dit tu veux ton pays, vote pour qu\u2019\u00e7a d\u00e9pende de toi\nL\u2019occasion se pr\u00e9sente deux fois\n\n[Refrain]\n\nD\u2019mande-toi pas pourquoi ya encore des gens qui s\u2019battent\nQuand dans leur propre pays leur langue reste un handicap\nEt si tu cherches des preuves, elles s\u2019r\u00e9v\u00e8lent parfois\nMais la majorit\u00e9 du peuple est aveugle par choix\n\nLa plan\u00e8te tourne autour d\u2019une seule musique\nMoi j\u2019refuse d\u2019accorder ma voix avec leur pens\u00e9e unique\nJ\u2019veux rester qui j\u2019suis, j\u2019veux qu\u2019tu restes qui t\u2019es\nIf you don\u2019t understand me on va devoir s\u2019quitter\n\nMoi ma langue est sous respiration subventionn\u00e9e\nJe l\u2019sais c\u2019est pas d\u2019ta faute si on aime pu qui on est\nPour qu\u2019les radios jouent du francophone faut les pousser\nNotre culture est une vieille fille que personne veut \u00e9pouser\n\nM\u00eame nous on danse avec une autre d\u00e8s qu\u2019on a la chance\nCombien d\u2019queb renient leur accent en France\nCombien disent c\u2019est pas grave, fais-en pas toute une montagne\nQuand depuis 1759, moi j\u2019ai perdu mon calme\n\nMais j\u2019ai vol\u00e9 les Hurons\nEt autres peuples qu\u2019eux seuls s\u2019rappellent du nom\nAb\u00e9naquis, Iroquois, Micmacs et Cris\nAinsi l\u2019histoire s\u2019\u00e9crit\n\nLes canons parlent, ceux qui en ont pas font d\u2019la place\nMais comme dirait Vigneault toutes les humains sont d\u2019ma race\nDemain j\u2019m\u2019\u00e9teindrai face \u00e0 d\u2019autres tribus qui naissent\nJ\u2019me souviendrai qu\u2019nos diff\u00e9rences sont richesse", "image": "https://images.genius.com/90aee7a4082fb9282ce3e526aa6c96c7.1000x1000x1.jpg"}], "artist": "Manu Militari"}