{"songs": [{"title": "Sultan Hotel", "album": "Mar\u00e9e Humaine", "year": "2012-09-11", "lyrics": "[Verse 1]\nOn aurait pu \u00eatre \u00e0 Rio, \u00e0 Manille ou \u00e0 Delhi\nDans n\u2019importe quel barrio que le soleil embellit\nOn est dans un pays ou r\u00e8gne une mis\u00e8re silencieuse\nAu centre d\u2019une ville bruyante qu\u2019on appelle la victorieuse\n\nD\u2019un h\u00f4tel o\u00f9 l\u2019prix d\u2019un lit varie selon l\u2019palier\nO\u00f9 logiquement les plus mal pris se tapent toute l\u2019escalier\n8 \u00e9tages, 40 degr\u00e9s, \u00e7a fait loin pour des smokes\nMais quand t\u2019es l\u00e0 d\u2019puis toujours, des fois c\u2019pas l\u2019tour des autres\n\nOn est comme une famille d\u00e9rout\u00e9e d\u2019notre karma\nLa vielle nipponne qui fait la bouffe on l\u2019appelle mama\nQu\u2019on vienne du Br\u00e9sil ou d\u2019la C\u00f4te d\u2019Ivoire\nOn s\u2019m\u00e9lange mais au final chacun sa propre histoire\n\nMohsen, lui il vit s\u2019ul top d\u2019l\u2019immeuble\nC\u2019est l\u2019gars qui ram\u00e8ne aux touristes la dope qui veulent\nLe reste du temps il leur fait des beaux yeux\nEsp\u00e9rant qu\u2019on l\u2019aide un jour \u00e0 bouger sous d\u2019autres cieux\n\nY\u2019aime autant son pays qui y en hait l\u2019fonctionnement\nY\u2019aimerait que l\u2019pr\u00e9sident finisse comme le pr\u00e9c\u00e9dent\nMais \u00e7a changerait quoi, faique y boit toute son malaise\nAvant d\u2019chercher l\u2019extase au fond du cul d\u2019une Soudanaise\n\nIbtissam, elle s\u2019nourrit rien qu\u2019d\u2019espoir\nElle dit qu\u2019m\u00eame en Afrique c\u2019pas plus facile d\u2019\u00eatre noire\nElle dit qu\u2019entre eux ya m\u00eame une hi\u00e9rarchie\nSelon les cheveux, la maudite p\u00e2leur ou l\u2019ethnie\n\nPis qu\u2019beaucoup d\u2019fr\u00e8res s\u2019renient ou s\u2019consid\u00e8rent comme arabe\nQuand souvent ici on les consid\u00e8re comme d\u2019la marde\nMohsen, lui dit qu\u2019elles veulent qu\u2019une banane ou qu\u2019une branche\nPis qu\u2019elles puent sauf que c\u2019est moins cher qu\u2019un cul d\u2019blanche\n\nTania, s\u2019d\u00e9hanche \u00e0 un jet d\u2019pierre d\u2019l\u2019h\u00f4tel\nJ\u2019l\u2019ai crois\u00e9e hier le temps d\u2019un pichet d\u2019bi\u00e8re\nElle exposait ses ressources ukrainiennes\nAu centre d\u2019une foule r\u00eavant d\u2019conqu\u00eates hitl\u00e9riennes\n\nElle avait d\u2019l\u2019air rien qu\u2019un peu plus lobotomis\u00e9e\nQue d\u2019habitude, p\u2019t\u2019\u00eatre \u00e0 force de s\u2019faire p\u00e9tro-domiser\nPar des formes de croyants mais sans accepter l\u2019fond\nTout juste bon \u00e0 prier jusqu\u2019\u00e0 s\u2019p\u00e9ter l\u2019front\n\n[Refrain]\nSultan H\u00f4tel\nSi tu y passes dis salam d\u2019ma part aux coquerelles\nM\u00e9fie-toi rien qu\u2019d\u2019la femme de m\u00e9nage Leila\nElle fouille tes bagages si t\u2019es surveille pas\n\n[Verse 2]\nHans, voyage \u00e0 travers le monde\nDepuis une couple de lunes, le soleil lui sert de montre\nUne \u00e9toile le guide sur les seins d\u2019M\u00e8re Nature\nIl s\u2019laisse nourrir de palmier, de plage et d\u2019faire d\u2019la pure\n\nYa toujours une broue avec un sourire aux l\u00e8vres\nIl r\u00e9p\u00e8te : chu un loup, le peuple un troupeau d\u2019ch\u00e8vres\nSi jamais \u00e7a vire mal, la seule issue j\u2019\u00e0 connais\nJ\u2019garde la derni\u00e8re balle pour moi comme un japonais\n\nIl Yabani, avait l\u2019regard brid\u00e9\nLa colonne toute pli\u00e9e, le restant du corps rid\u00e9\nIl s\u2019cherchait une peau d\u2019p\u00eache \u00e0 croquer comme \u00e7a y tente\nL\u2019imb\u00e9cile s\u2019tait tromp\u00e9 entre \u00c9gypte et Tha\u00eflande\n\nOn l\u2019a vu tra\u00eener partout ses yeux d\u2019cochons\nAvec ses grosses mains poilues salir des cheveux d\u2019gar\u00e7ons\nMais ya kharab baitou, la rue parle avec un accent d\u2019barbu\nLa rue dit maintenant qu\u2019un char l\u2019avait pas vu\n\nTrop d\u2019touristes sont l\u00e0 \u00e0 poireauter\nAttendant qu\u2019un local les invite boire un th\u00e9\nApr\u00e8s ils sont surpris d\u2019devoir acheter un tapis\nIls pensaient vraiment s\u2019\u00eatre trouv\u00e9 un ami\n\n\u00c0 part les pyramides toute Le Caire leur est interdit\nVu qu\u2019il s\u2019trouve derri\u00e8re les murs d\u2019leur fermeture d\u2019esprit\nComme les enfants d\u2019H\u00e9bron, ils connaissent pas l\u2019partage\nIls s\u2019tiennent qu\u2019entre colons, ils fr\u00e9quentent pas l\u2019sauvage\n\nMagdi, travaille \u00e0\u2019r\u00e9ception\nL\u2019air de dire : j\u2019vis sans r\u00eave faique sans d\u00e9ception\nToujours \u00e0 l\u2019h\u00f4tel, d\u2019vant l\u2019\u00e9cran douze pouces\nAvec une paye qui met pas souvent d\u2019poulet dans l\u2019couscous\n\nSa femme l\u2019appelle tellement qu\u2019ya pu l\u2019go\u00fbt d\u2019r\u00e9pondre\nMais sa grosse est t\u00eatue, \u00e7a sonne \u00e0 toutes les secondes\nFaique il blast le volume de son match de foot\nPis qu\u2019le reste d\u2019la plan\u00e8te aussi aille s\u2019faire foutre", "image": "https://images.genius.com/90aee7a4082fb9282ce3e526aa6c96c7.1000x1000x1.jpg"}], "artist": "Manu Militari"}