{"songs": [{"title": "Lisdexamph\u00e9tamine", "album": "Contr\u00f4le", "year": "2017-06-02", "lyrics": "[Intro : Lary Kidd & O.G. Bear]\nOuuuuuuu hmmmm  (I gotta)\n\n[Lary Kidd]Lary Kidd est dans le hood bitch\nLary Kidd est dans le hood bitch\nLary Kidd est dans le hood bitch\nLary Kidd est dans le hood bitch\nLary Kidd est dans le hood bitch\nLary Kidd est dans le hood bitch\nLary Kidd est dans le hood bitch\n[Back vocals]Gotta stay focus man\nThis roller coaster ride\nI'm on it, on the road again\nI gotta do it like that\nThis roller coaster ride\nI'm on it, on the road again\nI gotta do it like that\n[1er couplet]\nJ'ai des sueurs froides\nNervous breakdown\n\u00c7a fait plusieurs fois\nJ'ai voulu boire le whole bottle of vodka\nOublier la douleur de la maladie mentale\nToujours on tour, on est mal aliment\u00e9\nChill avec les bums qui sont encore about it\nLongue toge blanche comme un illuminati\nAvec le Ducks sign boy, Teemu Selanne\nI'll be damned if I let another man\nEssayer d'venir mettre la main\nSur ne serait-ce qu'une cenne qui m'appartient\nFuckboys qui sont greedy\nGotta keep it a hundred\nPis si tu fuck le bread\nC'est la cerise sur le sundae\nTous les jours, tous les jours, man j'reach pour le sommet\nPop a few xans quand j'reach pour le sommeil\nI be reppin' my city like a champ\nQuelques mauvaises habitudes font que j'suis serr\u00e9 pour le rent\nOn peut dire que la drogue dans mon cas, c'toujours un probl\u00e8me\nQuand j'me check dans l'miroir j'ai d'la mis\u00e8re \u00e0 me r'conna\u00eetre\nGot the baby mama stressin', je sais m\u00eame pu si elle m'tol\u00e8re\nMeanwhile, j'agis comme si tout allait \u00eatre alright\nI don't know man\nIt's a crazy world we live in, don't you think?\nToutes ces jolies filles got me thinkin' with my dick\nToute la soif de succ\u00e8s got me acting like a dick\nM\u00eame Manu qui est f\u00e9ministe, he had to blame it on a bitch\nAin't that bitch?\nO\u00f9 s'en va ma vie boy?\nTout ces questionnements got me sippin' on lean boy\nSippin' on lean got me actin' like I'm retarded\nRoam around town toute la nuit jusqu'\u00e0 huit heures\nTout \u00e7a pour l'argent\nLa route est longue jusqu'au succ\u00e8s, mais j'suis about it\nLa route est longue jusqu'au succ\u00e8s, mais j'suis about it\nTu t'mets dans mon chemin mo'fucker, tu t'fais empaler\nYeah, Imma do it like that\n\n[Hook]\nI gotta stay focus man\nThis roller coaster ride\nI'm on it, on the road again\nYeah-eh-eh (X6)\nI gotta do it like that, non non non\n\n[Bridge]\nOuais, tu peux l'mettre cinq, six fois, man\nCrazy shit about\nI gotta do it like that, I know\n\n[OG Bear]\nRoad again\nFocus man\nYeah\nFocus man\n\n[Outro]\nJ'ai des sueurs froides\nNervous breakdown\n\u00c7a fait plusieurs fois\nJ'ai voulu boire le whole bottle of vodka\nOublier la douleur de la maladie mentale\nToujours on tour, on est mal aliment\u00e9\nToujours on tour, on est mal aliment\u00e9\nOublier la douleur de la maladie mentale", "image": "https://images.genius.com/22c2f1d57a20a01fc9a9c394f91fbd43.1000x1000x1.jpg"}], "artist": "Lary Kidd"}