{"songs": [{"title": "Qu\u00e9bec libre", "album": "French Amerikkka", "year": "2018-11-23", "lyrics": "[Speech: Charles de Gaulle]\nCe soir, en ajoutant que j'emporte de cette r\u00e9union inou\u00efe\nDe Montr\u00e9al, un souvenir inoubliable\nLa France enti\u00e8re sait, voit, entend\nCe qui se passe ici\nEt je puis vous dire qu'elle en vaudra mieux\nVive Montr\u00e9al, vive le Qu\u00e9bec\nVive le Qu\u00e9bec libre\nVive le Canada fran\u00e7ais\nEt vive la France\n\n[Verse]\nJ'\u00e9tais un \u00e9tranger, et vous m'avez accueilli\nJ'savais pas o\u00f9 on s'en allait, mais on \u00e9tait d\u00e9barqu\u00e9 ici\nEspoir d'une meilleure vie\nEspoir d'un avenir meilleur\nUne chose que j'ai compris, c'est qu'on \u00e9tait des r\u00eaveurs\nCar la mis\u00e8re est partout\nViens faire un tour dans l'secteur\nLes Babylone qui patrouillent\nMoi j'pense \u00e0 Villanueva\nTu penses que tu l'sais, mais tu l'sais pas\nN\u00e9 aux \u00c9tats, jeune noir qu\u00e9b\u00e9cois\n\n[Bridge]\nGo\u00fbte \u00e0 [?] attache ta tuque, fait froid l'hiver\nOn dit souvent qu'c'est Dieu, mais souvent c'est Lucifer\nOn est pas diff\u00e9rent, on est pareil ou similaire\n[?] pis yo, esti qu'j'suis fier\nConscient des opportunit\u00e9s, conscient des privil\u00e8ges\nContent d'\u00eatre l\u00e0 pour l'unit\u00e9, j'fais \u00e7a pour le Qu\u00e9bec\nConscient des opportunit\u00e9s, conscient des privil\u00e8ges\nContent d'\u00eatre l\u00e0 pour l'unit\u00e9, j'fais \u00e7a pour le Qu\u00e9bec\n\n[Outro]\nVive le Qu\u00e9bec libre\nVive le Qu\u00e9bec libre\nVive le Qu\u00e9bec libre\nVive le Qu\u00e9bec libre\nFrench [?] Babylone, [?] MTL, Qu\u00e9bec, yeah, t'es dans ma zone\nVive le Qu\u00e9bec libre\nJ'me souviens quand j't'ais jeune, c'tait les fran\u00e7ais contre les anglophones\nVive le Qu\u00e9bec libre\nFrench [?] Babylone, [?] MTL, Qu\u00e9bec, yeah, t'es dans ma zone\nVive le Qu\u00e9bec libre\nJ'me souviens quand j't'ais jeune, c'tait les fran\u00e7ais contre les anglophones\nFrench [?] Babylone, [?] MTL, Qu\u00e9bec, yeah, t'es dans ma zone\nJ'me souviens quand j't'ais jeune, c'tait les fran\u00e7ais contre les anglophones\nFrench [?] Babylone, [?] MTL, Qu\u00e9bec, yeah, t'es dans ma zone", "image": "https://images.genius.com/aa406fd569eef5a18c84a3a7725902a4.959x959x1.jpg"}], "artist": "Sans Pression"}