{"songs": [{"title": "Diddy Kadhafi", "album": "A Trappin Ape", "year": "2016-12-16", "lyrics": "[Couplet 1 : Rowjay]\n\u00c0 chaque jour, je change de pays comme si je changeais de putain de v\u00eatements\nAvec mon crew, moi et mes gars sommes apr\u00e8s de cr\u00e9er un nouveau r\u00e9giment\nToutes ces bitch m'appellent mais je ne r\u00e9pond plus parce que je n'ai plus le temps\nJeune Diddy Kadhafi \u00e0 chaque fois que je sors les gens font des \u00e9v\u00e9nements\nFuck les saisons, m\u00eame en \u00e9t\u00e9 moi je porte du vison\nJ'suis le champion de ma propre division, ma vie c'est comme un Canal \u00c9vasion\nEnveloppe brune dans mon bureau, je parle pas de corruption\nMon gars Mederic se trouve en Afrique, il oeuvre dans la construction\nJ'signe mon nom sur les contrats\nAvec les juifs, j'suis \u00e0 une bar-mitsva\nAvec les arabes, je fume la chicha\nAvec les russes, nous on boit de la vodka\nJ'suis avec ta bitch en Italie, j'lui fais manger de la pizza\nJ'suis dans l'aile avec des ha\u00eftiens, on c\u00e9l\u00e8bre on danse le Konpa\nDeux Geishas, \u00e0 mes pieds, nettoient mes Margiela, oui mes souliers\nSur mon tr\u00f4ne, elles me donnent \u00e0 manger\nJe les cuddle, elles adorent Rowjay\nSur ma casquette le nom de mon \u00e9quipe, je crois qu'on ne peut nous tester\nJ'suis sur NYC check mon fr\u00e8re Louis (Or\u00e9e), on fait du pr\u00eat-\u00e0-porter\nJeune Rowjay\n\n[Refrain]\nJ'suis bien pos\u00e9 dans une berline\nAvec ma connexion maghr\u00e9bine\nDiddy Kadhafi, riche comme C\u00e9line\nDiddy Kadhafi, riche comme C\u00e9line\n\n[Couplet 2 : Rowjay]\nQuand je sors de l'avion, on me d\u00e9roule un tapis\nJe re\u00e7ois un accueil digne de Khadafi en Libye\nMon plug Mehdi m'appelle, il est pos\u00e9 en Alg\u00e9rie\nJe prends le prochain vol, moi je ball comme Kobe\nMon plug Ali m'appelle, il a ce que que tu veux, il se retrouve en Arabie\nJ'suis dans une suite avec deux bitch, deux amies qui sont devenus bi\nC'est fou devant ce qu'elles font lorsqu'elles voient tous ces llet-bi\nLes ha\u00eftiens les traitent de bouzin, les arabes les traitent de zebi\nJe ne bois plus vraiment de sirop, j'ai arr\u00eat\u00e9 de sip du lean\nJ'ai du succ\u00e8s dans tout ce que je fais, faut dire que ma vie c'est le spleen\nJ'suis ce jeune homme brillant qui ferait tout pour nourrir ses jeunes brigands\nRoule dans une S600, fais attention \u00e0 toi parce que moi j'\u00e9crase tous ces fain\u00e9ants\nBien pos\u00e9 dans un resto, la facture coute le prix d'une merco\nLa merco coute plus cher que ton condo\nOeuvres d'art sur mes murs, George Condo\nUn jour j'serai partout dans le monde, j'serai sur Sarajevo\nEn train de fumer des cigares avec mes gars de Monaco\nJeune Rowrow\n\n[Refrain]\nJ'suis bien pos\u00e9 dans une berline\nAvec ma connexion maghr\u00e9bine\nDiddy Kadhafi, riche comme C\u00e9line\nDiddy Kadhafi, riche comme C\u00e9line", "image": "https://images.genius.com/79d0c93ccc15ae4b0964213a30b5a57a.699x699x1.jpg"}], "artist": "Rowjay"}