{"songs": [{"title": "Fuck Fame", "album": "Confession risqu\u00e9e", "year": "2017-11-01", "lyrics": "[Hook: Icey Da Zoe]\n[?]\n\n[Verse 1: Icey Da Zoe]\n[?]\n\n[Hook: Icey Da Zoe]\n[?]\n\n[Verse 2: White-B]\nElle sait qu'devant l'inspecteur, il faut s'taire\nElle sait d\u00e9j\u00e0 qu'c'est capuch\u00e9 qu'on op\u00e8re\nBen ouais, je sais qu'c'est trop tard\nGrosse poursuite, y'a m\u00eame des h\u00e9licopt\u00e8res\nLa diff\u00e9rence, depuis plus rien n'me fascine\nElle veut ma bite, non elle veut pas des bisous\nDans la rue, ton ami, c'est celui qui t'assassine\nT'es m\u00eame pas du calibre, et tu viens parler d'visou\nLa rue t'r\u00e9serve la mort ou bien la prison\nJ'en ai marre de voir mes parents \u00e9puis\u00e9s\nMais j'voyais pas les barreaux dans ma vision\nLa vie, un test o\u00f9 j'ai jamais r\u00e9vis\u00e9\nIci, la haine finit en homicide\nJ'r\u00eave des Cara\u00efbes quand j'me r\u00e9veille gros j'suis encore ici\nPetit, aies pas peur de faire du cash, non, non\nPetit, aies pas peur de t'envoler [?]\nC'est le jour de paye, on roule en Benz, Benz\nSi c'est l'heure du verdict, j'prendrai ma peine, peine\nC'est le jour de paye, on roule en Benz, Benz\nSi c'est l'heure du verdict, j'prendrai ma peine, peine\n\n[Hook: Icey Da Zoe]\n[?]", "image": "https://images.genius.com/16b2a200fc5af4ad3d15504323e396f3.956x956x1.jpg"}], "artist": "WHITE-B"}