{"songs": [{"title": "Intro", "album": "Confession risqu\u00e9e", "year": "2017-01-01", "lyrics": "Yaa (Yaa, ya, ya)\nWhite-B\nNon ici \u00e7a parle plus tu fais l'fou \u00e7a faya (RA, ROW)\nGros j'te jure sur ma vie\nCes rappeurs de merde feront jamais honneur \u00e0 la ville\nJ'ai connu l'karma vite\nL'inspecteur veut m'avoir car j'fais mouiller la chatte \u00e0 sa fille\nL'\u00e9quipe est \u00e0 l'affiche\nBeaucoup manque \u00e0 l'appel depuis l'beat Parastites\nJamais personne t'assiste\nTout l'monde fais la guerre pour avoir son p'tit coin d'paradis\nTous grandi dans l'bloc, l'\u00e9quipe est pr\u00eate \u00e0 d\u00e9placer des montagnes\nHennesy dans l'cup\nJ'arrive dans l'club, je pars avec celle qui t'accompagne\nPour ceux qui croyaient qu'j'\u00e9tais gentil\nMa haine s'ressentera dans mes rafales\nOuais c'est l'monde \u00e0 l'envers\nMaintenant j'vois les petits investir dans des pare balle\n\nViens dans l'trap y'a tout les drogues c'est varier-\u00e9-\u00e9\u00e9\u00e9\nDepuis tout p'tit les armes on sait les manier-\u00e9-\u00e9\u00e9\u00e9\nTu faire du cob par tout les mani\u00e8r-\u00e8re-\u00e8re\nMaman j'm'excuse mais \u00e0 la rue j'suis mari\u00e9-\u00e9-\u00e9\u00e9\u00e9\n\nNon ici \u00e7a parle plus tu fais l'fou \u00e7a faya (Faya) (RA, ROW)\nChacun sa liasse ouais chacun fais ses bhay-e\nSi la police me cherche j'dirais qu'j'me barre en voyage\n(O, Ouais) J'ai vu la mort couper en d\u00e9tail-e\n\nNon ici \u00e7a parle plus tu fais l'fou \u00e7a faya (Faya) (RA, ROW)\nChaque homme \u00e0 ses peines et chaque homme \u00e0 ses failles-e\nTu apprend \u00e0 nager en \u00e9vitant la noyade (noyade)\nOn change pas notre point d'vu mais malgr\u00e9 qu'on d\u00e9raye-e (raye-e)\n\nPlus t'arr\u00eate de t'affoler\nJ'sais t'es juste la pour d\u00e9corer\nPerdu dans mes folies alcooliques\nY'a qu'le bout sur la tempe qu'on peux m'r\u00e9soner (Raa)\nSi j't'ai fais du mal d\u00e9soler\nMais j't'ai juste un cas isol\u00e9\nBienvenue dans notre syst\u00e8me de merde ou tu prend plus de temps \u00e0 voler qu'a violer\nLes yeux riv\u00e9s vers le sablier\nOn compte l'argent le temps et les munitions\nTr\u00e8s conscient qu'la peux vite arriv\u00e9e\nTu disparais bien plus vite qu'une illusion (x2)\nToujours tremp\u00e9 dans de sales histoires\nPetit porte tes couilles car m\u00eame si t'as des gans tes mains sont pas \u00e0 l'abris d'\u00eatre salissable\nPour nourrir ses proches chacun sa recette\nY'a c'lui qui parle et c'lui qu'i'agit\nY s'ront tous la quand tu s'ra refait\nLe prix d'la mort c'est c'lui d'la vie\nOn cours apr\u00e8s l'argent facile\nDes fr\u00e8res en prison ou \u00e0 l'asile\nLe canon cach\u00e9 chez la voisine\nEt si tu veux tester j'te dis va-y\n\nNon ici \u00e7a parle plus tu fais l'fou \u00e7a faya (Faya) (RA, ROW)\nChacun sa liasse ouais chacun fais ses bhay-e\nSi la police me cherche j'dirais qu'j'me barre en voyage\n(O, Ouais) J'ai vu la mort couper en d\u00e9tail-e\n\nNon ici \u00e7a parle plus tu fais l'fou \u00e7a faya (Faya) (RA, ROW)\nChaque homme \u00e0 ses peines et chaque homme \u00e0 ses failles-e\nTu apprend \u00e0 nager en \u00e9vitant la noyade (noyade)\nOn change pas notre point d'vu mais malgr\u00e9 qu'on d\u00e9raye-e (raye-e)", "image": "https://images.genius.com/16b2a200fc5af4ad3d15504323e396f3.956x956x1.jpg"}], "artist": "WHITE-B"}