{"songs": [{"title": "Avenue", "album": "Long Jeu", "year": "2016-10-21", "lyrics": "[Hook]\nAh comme c'est fuckin' bon\nD'\u00eatre fuckin' back sur le ave\nAh comme c'est fuckin' bon\nD'\u00eatre juste fuckin' back sur le ave\nAh comme c'est donc bon\nD'\u00eatre juste fuckin' back sur le ave\nComme c'est fuckin' bon\nD'\u00eatre juste fuckin' back sur le ave\nComme c'est fuckin' bon\nD'\u00eatre juste fuckin' back sur le ave\nAh comme c'est donc bon\nD'\u00eatre juste fuckin' back \u00e0 la maison\nMy nigga dit\nAh comme c'est fuckin' bon\nD'\u00eatre juste fuckin' back sur le ave\n\n[Verse 1]\nAh comme c'est fuckin' bon d'\u00eatre juste back sur la map\nFuck it, ah comme c'est donc ben apaisant juste la pr\u00e9sence d'une femme\nWe still yung mon gars\nCombien c'qui a encore d'cobayes en lignes pour le lab?\nD'autres stocks ont drop icitte\nD'autres jeunes braves ont pris la rel\u00e8ve, d\u00e9j\u00e0 mais l\u00e0\nMalgr\u00e9 tout c'est bon d'\u00eatre \u00e0 nouveau sur le ave\nQuand j'passe par l\u00e0, j'prends une pause devant l'ruisseau\nPour mon patnais doing time\nPis \u00e7a fait un boutte qu'y'est rentr\u00e9\nY'avaient pas encore sorti l'dab\nNi Donald Chump, ni la joke des nouveaux Adidas Hochelag', hey yo, hey yo\nDans pas long \u00e7a va \u00eatre fini pis y va \u00eatre out\nFuckin' presque exactement une demi-ann\u00e9e\n\u00c7a c'est si y s'tient relaxe, so l\u00e0 pourra dire :\n\n[Hook]\nAh qu'c'est fuckin' bon\nD'\u00eatre back sur le ave\nAh comme c'est fuckin' bon\nD'\u00eatre fuckin' back sur le ave\nAh comme c'est donc bon\nD'\u00eatre juste fuckin' back sur le ave\nComme c'est fuckin' bon\nD'\u00eatre juste fuckin' back sur le ave\nAh comme c'est fuckin' bon\nD'\u00eatre juste fuckin' back sur le ave\nAh comme c'est donc bon\nD'\u00eatre juste fuckin' back \u00e0 la maison\nMy nigga dit\nAh comme c'est fuckin' bon\nD'\u00eatre juste fuckin' back sur le ave\n\n[Verse 2]\nQuoi d'bon \u00e0 cantine?\nL'\u00e9poque du troc est pas dead\nPush-ups tous les jours\nLa porte du coeur a sera pas flat\nL'fuckin' jour arrive, clean tu t'habilles\nY vas pas en ligne, c'coup-l\u00e0 y'ouvrent les grilles\nAh shit, what a day!\nUne claque d'air libre sur ta face\nR'tourner voir les p'tits amours\n\u00catre l\u00e0, les regarder shine\nJ'veux dire :\nNos bijoux d'famille sont fuckin' pas nos bagues\nApr\u00e8s tout, peu importe\nTe v'l\u00e0 d'retour pimpant\nPapa p\u00e9p\u00e9\nM\u00eame pas perdu comme \u00e7a devrait\nTu s'ras pas l'premier d'la gang \u00e0 pull un rue des Braves\n\u00c9coute-moi donc l\u00e0 l\u00e0\n\n[Hook]\nAh comme c'est fuckin' bon\nD'\u00eatre juste fuckin' back sur le ave\nAh comme c'est fuckin' bon\nD'\u00eatre juste fuckin' back sur le ave\nAh comme c'est donc bon\nD'\u00eatre juste fuckin' back \u00e0 la maison\nMy nigga dit\nAh comme c'est fuckin' bon\nD'\u00eatre juste fuckin' back sur le ave\nComme c'est fuckin' bon\nD'\u00eatre juste fuckin' back sur le ave\nComme c'est fuckin' bon\nD'\u00eatre juste fuckin' back sur le ave\nAh comme c'est donc bon\nD'\u00eatre juste fuckin' back \u00e0 la maison\nMy nigga dit\nAh comme c'est fuckin' bon\nD'\u00eatre juste fuckin' back sur le ave\n(...)\nLa vie est pleine d'avenues mon chum\nBack sur le ave", "image": "https://images.genius.com/ab21aacede9f8eb2d488391ba86a42a1.1000x1000x1.jpg"}], "artist": "KenLo"}