{"songs": [{"title": "S\u00e9curise le sac", "album": "Tu sais, vol. 1", "year": null, "lyrics": "[Intro]\nTu sais\nZoow\n\n[Refrain]\nJ's\u00e9curise le sac (Zoow)\nEnsuite j'remets deux (Ciao)\nTout ce qu'j'connais c'est l'trap (J'ai quelques mouvements frauduleux)\nPense pas que mon BTCL a pour sac (Noon ! Le technar est en feu)\nJ'fais des traps et des outs sans permis, j'suis tr\u00e8s audacieux (Tu sais !)\n\n[Couplet 1]\nAucune livraison ce mois-ci, des fois j'suis paresseux\nJ'ai pas besoin d'te dire que j'dors pas, tu vas le voir dans mes yeux\nParce que le sol est dans mes veines, le grind est dans mes cernes (Cernes !)\nSi j'te donne un props, c'est juste question d'hygi\u00e8ne (... Zoow ! Ta pute vaut pas la peine !)\nC'est juste pour quelques dollars qu'elle rentre de l'caille et te fait une sc\u00e8ne\nEt-et moi j'aime les plantes, c'que l'on r\u00e9colte on s\u00e8me\nCes sacs l\u00e0 ont suppos\u00e9ment \u00e9t\u00e9 faits juste pour sandwich (Zow !)\nMoi j'les prit, et j'ai rendu \u00e7a botanique (Tu sais !)\nJ'vais pas t'mentir, dans spot : y'a quelques mouvements \u00e9rotiques\nSi c'est pas un [XXX], si c'est la gang et y'a un orgie (Gang !)\n\n[Refrain]\nJ's\u00e9curise le sac (Zoow)\nEnsuite j'remets deux (Ciao)\nTout ce qu'j'connais c'est l'trap (J'ai quelques mouvements frauduleux)\nPense pas que mon BTCL a pour sac (Noon ! Le technar est en feu)\nJ'fais des traps et des outs sans permis, j'suis tr\u00e8s audacieux (Tu sais !)\nJ's\u00e9curise le sac (Zoow)\nEnsuite j'remets deux (Ciao)\nJ's\u00e9curise le sac (Zoow)\nEnsuite j'remets deux (Ciao)\nJ's\u00e9curise le sac (Zoow)\nEnsuite j'remets deux (Ciao)\nTout ce qu'j'connais c'est l'trap (Trap !)\n\n[Couplet 2]\nJ'suis pas mind, j'continue \u00e0 grind, le trap c'est mon caille\nJ'ai d'l'\u00e9caille, tour du poignet maintenant on dirait de l'aille\nPasse moi l'paille, le mois pass\u00e9 j'ai book en [XXX], c'est un vibe\nJ'ai pris ta moune et j'l'ai mise sur un flight : Yah j'suis fly\nPas d'atterrissage quand j'd\u00e9colle (Tu sais)\nJ'lit pas trop mais j'ai des livres dans mon sac d'\u00e9cole\nT'inqui\u00e8te pas toi j'ai s\u00e9curis\u00e9 tant le [XXX] il [XXX] son V (Zow !)\nC'est le quadrilat\u00e8re : il neige l'\u00e9t\u00e9, c'est chaud l'hiver (Tu sais !)\nNon personne il berne, au t\u00e9l\u00e9phone j'emploie des termes (Ah !)\nNos mains sont remplies de germes, on les lave quand le trap il ferme (On trap !)\nJ'viens de recevoir un text, \u00e7a parle encore de sexe\nSauf que cette fois c'est pour moi mais j'm'en fous, j'vais la laisser s'doigte (Zow)\n\n[Refrain]\nJ's\u00e9curise le sac (Zoow)\nEnsuite j'remets deux (Ciao)\nTout ce qu'j'connais c'est l'trap (J'ai quelques mouvements frauduleux)\nPense pas que mon BTCL a pour sac (Noon ! Le technar est en feu)\nJ'fais des traps et des outs sans permis, j'suis tr\u00e8s audacieux (Tu sais !)\nJ's\u00e9curise le sac (Zoow)\nEnsuite j'remets deux (Ciao)\nJ's\u00e9curise le sac (Zoow)\nEnsuite j'remets deux (Ciao)\nJ's\u00e9curise le sac (Zoow)\nEnsuite j'remets deux (Ciao)\nTout ce qu'j'connais c'est l'trap (Trap !)", "image": "https://images.genius.com/f71620b33553063e155c2c1063a5d84a.300x300x1.jpg"}], "artist": "Tizzo"}