{"songs": [{"title": "GADONBIN", "album": "Jeu De Puissance", "year": "2011-12-29", "lyrics": "[Intro]\nAnticipateurs (OUINNNN)\nDeep dans l'game (OUINNNN)\nHey yo Monak (OUINNN)\nHey yo Tronel\n\n[Chorus]\nGadonbin (ouin), gadonbin (ouin)\nLes Anticipateurs, fuck that on r'vient (ahen)\nAh ben kin (ah ben), gadonbin (or'garde)\nJ'ai fum\u00e9 pleins d'joints mais j'sais pas combien (hehehe)\nAh ben kin (ah ben), gadonbin (or'garde)\nSi t'\u00e9tais Indien tu s'rais Algonquins (ouin)\nAh ben kin (ouin), gadonbin (ouin)\nQuand ta blonde \u00e0 vient, j'ai les ballons pleins\n\n[Verse 1: MC Monak]\nOn n'est noy\u00e9e dans bi\u00e8re, on est l\u00e9gendaire\nQuand qu'on rap, \u00e7a rends monoc R\u00e9gean fier (ouin)\nM'a t'j't\u00e9 dans foule (ok), j'suis R\u00e9gean Houle\nFlow trop \u00e9lectrisant m'a p\u00e9ter des ampoules (ohhh)\n\nHey yo Monak (ouin), hey yo Monak\nJ'peux-tu t'prendre en photo avec mon gros Kodak (ok)\nC'est ben d'valeur, c'est ben d'valeur\nLe gros sur ta personne tu n'as rien d'valeurs\n\nJ'suis back dans l'jeu (ouin)\nJ'te craque en deux (ouin)\nCombien d'sortes tu veux j'en ai 42\nHey yo le gros tu peux me retrouver entre 2 culs\nJe suis client r\u00e9gulier chez les danseuses nues\n\nTon style, c'est d'appeler les polices\nNotre \u00e9quipe est ben trop pro pour recruter des novices (d\u00e9calice)\nOn est back dans l'jeu (dans l'jeu), on est back dans l'jeu\nTo\u00e9 tu fais pousser du pots, MC Monak (j'en veux)\n\n[Chorus]\n\n[Verse 2: MC Tronel]\nOn est deep dans l'game (ouin), on est profonds dans l'jeu (ouin)\nLe gros j'p\u00eache de la truite pis du saumon quand j'veux (ok)\nJ'mange un T-Bone steak (ouin) a'c une pinte de rousse (ouin)\nT'es rims co\u00fbtent 1 piastre 45 le pouce (ohh)\n\nHey yo Tronel, hey yo Tronel\nJ'peux-tu avoir ton autographe sur mes bottes Sorel (oui monsieur)\nD\u00e9calice, le gros d\u00e9calice\nJ'investis dans l'immobilier pis j'ach\u00e8te des b\u00e2tisses\n\n150 piastres, 150 piastres\nC'est \u00e7a qu'il'me faut en essence pour que mon F-150 trace\nJuste 50 piastres, juste 50 piastres\nC'est \u00e7a que ta blonde charge pour qu'un gars y vient dans face\n\nMa notori\u00e9t\u00e9 est exponentielle (ouin)\nQuand j'meurs j'vais rejoindre les Expos dans l'ciel (oui monsieur)\nTa blonde g\u00e9mit comme une antilope qui baise\nElle l'aime les barres de chocolats Henry Rodriguez\n\n[Chorus]\n\n(#OUIN)", "image": "https://images.rapgenius.com/b3e3232757fe70fe60e1fb61908dfcd1.960x640x1.jpg"}], "artist": "Les Anticipateurs"}