{"songs": [{"title": "Kurt Cobain", "album": "Les Archives Vol.3", "year": "2016-01-29", "lyrics": "[Intro]\nCarl, montes le volume un peu d'ma voix\nPasses-moi l'feu\nOk...\n\n[Verse 1]\n\u00c7a fait...\nRapper dans l'mic pour m'emp\u00eacher de les fusiller\nChaque parole, c'est comme si j'mauto-mutilais\nMontes le volume on entend rien dans l'fond\nJ'vais les crever jusqu'au dernier comme la faim dans l'monde\nJ'suis dans un nuage de fumer j'ai le pied dans l'fond\nJe suis fou pardonnez-moi si j'ai saut\u00e9 dans l'feu\nSois pr\u00e9par\u00e9 si tu veux jouer dans l'jeu\nJ'ai pas de piti\u00e9 pour les rappeurs quand j'les brise en deux\nI'm a fuckin' Kurt Cobain, love is love, pain is pain\nJe suis sans piti\u00e9, man je suis blacklist\u00e9\nJe suis banni depuis qu'j'ai les pieds dans l'syst\u00e8me\nJ'ai mon Nirvana avec ma Courtney Love\nJ'veux la voir compter mon argent pendant que j'smoke des buzz\nJ'vois la rue, la souffrance dans les yeux des potes\nJe leur aurait donn\u00e9 tout c'que j'ai pas\n\n[Hook]\nI'm a fuckin' Kurt Cobain, \u00e7a va, allez b\u00e9b\u00e9 it's okay\nJ'ai des lunettes fum\u00e9es quand j'suis trop d\u00e9fonc\u00e9\nFast life chaque seconde est compt\u00e9e\nBitch, I'm a fuckin' Kurt Cobain, \u00e7a va, allez b\u00e9b\u00e9 it's okay\nOn parlera plus tard, laisses-moi compter mon bl\u00e9\nRemplis l'sac de sport, ce soir on affiche complet\n(Je suis un fuckin' Kurt Cobain)\nLove is love, pain is pain\n(Motherfuckin' Kurt Cobain)\nLove is love, pain is pain\n(Motherfuckin' Kurt Cobain)\nLove is love, pain is pain\n(KURT COBAIN!)\nAppelles-moi Soldat (KURT COBAIN!)\n\n\n[Verse 2]\nLes vrais hommes ont peur de personne\nJ'ai les oreilles bouch\u00e9es quand la police me questionne\nParait qu'j'ai des gars recherch\u00e9s par Interpol\nLes salopes qui parlent trop, je ne les tol\u00e8re pas\n24 sur 24 j'ai des fils de putes qui paranoyent\nAlors, \u00e0 ceux qui m'ont prit pour un rappeur \u00e0 la mode\n2016 ils ne vont rien comprendre\nMorts ou vivants, ils ne veulent que la r\u00e9compense\nI'm a fuckin' Kurt Cobain, j'ai connus des fuck\u00e9s qui ont finis surdos\u00e9s\nPrenez garde \u00e0 vous, ce soir il va y avoir des morts\nDepuis l'temps que j'vend des CD, j'connais la valeur des mots\nJe n'ai pas le temps de me la couler douce\nJe vis ma vie entre les rappels et la roulette russe\nJe prend des coups, les poulets m'ont mit sur \u00e9coute\nJe marcherai sur mes deux jambes et jamais sur mes coudes\n\n[Hook]\nI'm a fuckin' Kurt Cobain, \u00e7a va, allez b\u00e9b\u00e9 it's okay\nJ'ai des lunettes fum\u00e9es quand j'suis trop d\u00e9fonc\u00e9\nFast life chaque seconde est compt\u00e9e\nBitch, I'm a fuckin' Kurt Cobain, \u00e7a va, allez b\u00e9b\u00e9 it's okay\nOn parlera plus tard, laisses-moi compter mon bl\u00e9\nRemplis l'sac de sport, ce soir on affiche complet\n(Je suis un fuckin' Kurt Cobain)\nLove is love, pain is pain\n(Motherfuckin' Kurt Cobain)\nLove is love, pain is pain\n(Motherfuckin' Kurt Cobain)\nLove is love, pain is pain\n(KURT COBAIN!)\nAppelles-moi Soldat (KURT COBAIN!)\n\n\n[Verse 3]\nJe leur montrerai la limite\nMontres-moi ton cul, fais pas ta C\u00e9line\nIci le grand m\u00e9chant loup blanc d'Am\u00e9rique\nSi tu veux la guerre jamais \u00e7a fini\nPain is pain, j'\u00e9cris des chansons\nD\u00e9pose ton gun et donnes-moi des ailes\nB\u00e9b\u00e9 je l'sais bin, qu'on est pas riches\nOn travaille fort, b\u00e9b\u00e9, chaque jours on essaye\n\n[Outro]\nJ'perd un peu le contr\u00f4le de moi\nHen Hen\nCarl, coupes la musique mon pote\n\nI'M A FUCKIN' KURT COBAIN", "image": "https://images.genius.com/a9eedbf7a5844a01492fa2e1586699d0.600x600x1.jpg"}], "artist": "Souldia"}