{"songs": [{"title": "Pour toujours", "album": "Ad Vitam Aeternam", "year": "2017-10-06", "lyrics": "[Verse 1]\n\nForever, pour toujours\nJe les remercies pour tout\nPour le love, pour le hate\nTout \u00e7a ma donn\u00e9 la force de continuer jusqu'au bout\nTu peux photographier ma face\nFuck you, je n'est pas la t\u00eate \u00e0 sourire\nGros, je n'est jamais vendu mon ass\nMoi j'ai juste assur\u00e9 quand fallait assur\u00e9\nIls ne pourront jamais me censur\u00e9\nC'est fils de putes, qu'ils aillent se faire encul\u00e9\nJ'entre dans le club, je brise le micro\nJe crache le feu, je transforme les flammes en fum\u00e9s\nJ'offre des fleurs fan\u00e9es pour le mariage\nToujours dans un coin noir \u00e0 compter ma liasse\nPiratage dans cette industrie de merde\nJe fait le bruit d'un train d'enfer en d\u00e9raillage\nForever, \u00e0 jamais\nTu ne peux me rattraper\nLe prince du mordor ouvre les portes pour une nuit d'orgie dans le palet\nPuissant, trop lourd, balaise\nJe suis reparti pour un tour de man\u00e8ge\nOn va s'dire les vrais choses : J'le fait pour le love, mais j'le fait beaucoup plus pour le salaire\n\n[Refrain]\n\n\u00c0 tout jamais dans les livres\nGrossi\u00e8ret\u00e9s entre les lignes\nSexe, violence, adr\u00e9nalines\nJ'ai pass\u00e9 ma life \u00e0 prendre des risques\nFais stop si le disque bug\nLe rap ce n'est pas fait pour toi, n'insiste pas\nTrop de emcee's sur ma liste noire\nOn fait les choses, on prend le monnaie, on d\u00e9crisse de l\u00e0\n\nGarde un \u0153il sur moi\nLentement, mais surement\nImmortel, push it to the limit, prend de l'altitude\nAd Vitam Aeternam\nOn peut pas plaire \u00e0 tout l'monde (Pour toujours, \u00e0 jamais)\nNon, non, non\n\n\n[Verse 2]\n\n\u00c0 jamais, \u00e9ternel (Pour toujours)\nCicatrices et s\u00e9quelles\nEnfin un peu de lumi\u00e8re apr\u00e8s que j'aille pass\u00e9 toute ma vie dans les t\u00e9n\u00e8bres\nJe verse la gazoline (Met le feu !)\nL'atmosph\u00e8re est chaotique\nTu ne peux placoter sur mon dossier\nJe suis un gars s\u00e9rieux, je suis un gars solide\nGrav\u00e9 dans les m\u00e9moires de la musique\n\u00c0 la lame de rasoir sur le pupitre\nJe frappe le c\u0153ur en premier, la mort est stupide\nQue l'on trinque \u00e0 nos gal\u00e8res, \u00e0 nos bagarres\n\u00c0 nos squelettes de cach\u00e9s dans l'd\u00e9barras\n\u00c0 tout mes soldats qui s'd\u00e9placent dans les shows\nLaisse, laisse moi leurs passer la puff\nOn na\u00eet, on vie, on s'\u00e9vapore\nAlors profite des moments quand \u00e7a rapporte\nArr\u00eate de parler, gros surveille tes propos\nLe gang c'est la famille, respecte le logo\nOn retrouve des rappeurs noy\u00e9s dans le corr\u00e8ge\nJe crache dans le mic et j'te d\u00e9fonce le thorax\nOn a tous une limite \u00e0 \u00eatre bonasse\n\n[Refrain]\n\n\u00c0 tout jamais dans les livres\nGrossi\u00e8ret\u00e9s entre les lignes\nSexe, violence, adr\u00e9nalines\nJ'ai pass\u00e9 ma life \u00e0 prendre des risques\nFais stop si le disque bug\nLe rap ce n'est pas fait pour toi, n'insiste pas\nTrop de emcee's sur ma liste noire\nOn fait les choses, on prend le monnaie, on d\u00e9crisse de l\u00e0\n\nGarde un \u0153il sur moi\nLentement, mais surement\nImmortel, push it to the limit, prend de l'altitude\nAd Vitam Aeternam\nOn peut pas plaire \u00e0 tout l'monde (Pour toujours, \u00e0 jamais)\nNon, non, non\n\nGarde un \u0153il sur moi\nLentement, mais surement\nImmortel, [?] limite, prend de l'altitude\nAd Vitam Aeternam\nOn peut pas plaire \u00e0 tout l'monde (Pour toujours, \u00e0 jamais)\nNon, non, non\n\n[Instrumental]", "image": "https://images.genius.com/21d94593a838e915f7dbc0cd40aac9d8.720x720x1.jpg"}], "artist": "Souldia"}