{"songs": [{"title": "Le but", "album": "Le Qu\u00e9bec est mort, vive le Qu\u00e9bec!", "year": "2009-04-18", "lyrics": "Icitte au Qu\u00e9bec y fait pas froid : y fait frette\nC\u2019est de m\u00eame parce que c\u2019est de m\u00eame\nPis c\u2019est ben correct\nOn a de la place en masse\nPis nos face-\u00e0-face on les fait sur la glace\nAlors, on lace nos patins pis nos casques\nEt comme maurice, on glisse dans l\u2019ar\u00e8ne\nAvec la haine de la d\u00e9faite\nEt le feu dans les yeux\nEn fait, quand on veut, on peut\u2026\n\nGagner !\n\nEn des temps si lointains qu\u2019les francos\nS\u2019appelaient canadiens\n\u00c0 une \u00e9poque o\u00f9 les pucks \u00e9taient fait de crottin\nOn a r\u00e9uni des hommes dont le destin commun\nEst comme un film sans fin\nEn technicolor et tricolore\nBleu comme le st-laurent\nBlanc comme l\u2019hiver\nRouge comme le sang qui nous coule \u00e0 travers\nLe corps de l\u2019\u00e9quipe c\u2019est le coeur de la nation\nEt chaque ann\u00e9e faut clore avec une c\u00e9l\u00e9bration\n\nIls l\u2019diront jamais tel quel aux nouvelles\nMais le tissu social de montr\u00e9al\nC\u2019est de la sainte-flanelle\nQuand y est question de hockey\nNous on fait pas dans la dentelle, ok\nC\u2019est plus qu\u2019un sport\nC\u2019t\u2019une m\u00e9taphore de notre sort\nC\u2019est \u00e7a qui nous ressemble\nC\u2019est \u00e7a qui nous rassemble\nAnglo, franco peu importe ta couleur de peau\nSi tu d\u00e9testes toronto\nLe sang qui bouge dans tes art\u00e8res\nEst aussi rouge, mon fr\u00e8re, que les chandails de nos\n\n20 coeurs de vainqueurs\nQui luttent avec honneur\nLes canadiens pour une fois\nRallient tous les qu\u00e9b\u00e9cois\n20 coeurs de vainqueurs\nPour le pire et le meilleur\nLes canadiens de montr\u00e9al\nNotre \u00e9quipe nationale\n\nUn plan de match qu\u2019on respecte \u00e0 la lettre\nUn gardien alerte\nDes bonnes mises en \u00e9chec\nDes passes drettes sur la palette\nPis des lancers pr\u00e9cis et secs\nC\u2019est comme \u00e7a qu\u2019on va gagner nos \u00e9paulettes\n\nMais quand \u00e7a va mal, quand on cale ou on d\u00e9vire\nQue je voie pas un sale quitter le pont du navire\nC\u2019pas \u00e0 matin, qu\u2019on accroche nos patins\nUn flying frenchman, franchement ! \u00c7a franchit sans flancher\n\nAllez-y les habitants !\nQuand vous la mettez dedans\nY a un petit peu de nous autres l\u00e0-dedans\nOn est debout, avec vous\nOn ira jusqu\u2019au bout\nDurant la saison, c\u2019est toute la nation\nQui vibre au m\u00eame diapason\n\nComme quand les gens criaient : guy ! guy ! guy !\nC\u2019\u00e9tait en d\u00e9pit du combat constant de la vie\n\u00c7a leur donnait des forces\nY pouvaient bomber le torse\nVoil\u00e0 l\u2019amorce d\u2019un ralliement r\u00e9ussi\nOn peut\u2026\n\nGagner ! on veut plus que participer, nous on veut\nGagner ! \u00c0 soir on fonce sur la patinoire pour\nGagner ! si on se d\u00e9fonce pour la victoire, on va\nGagner ! on va gagner !\n\nEnfin on fait les s\u00e9ries, fini les folies\nL\u00e0 c\u2019est baston et rififi\n\nBoston, Philadelphie\nAvec les fant\u00f4mes du forum\nOn n\u2019a pas peur de personne\nChaque homme donne le maximum\nPour que cette ann\u00e9e soit la bonne\n\nAu printemps la fi\u00e8vre est universelle\nPis y a juste une place o\u00f9 la glace y faut pas qu\u2019a d\u00e9g\u00e8le\nIci le sang c\u2019est de la s\u00e8ve qui monte jusqu\u2019\u00e0 nos l\u00e8vres\nLe cri se change en un chant de ralliement qui s\u2019\u00e9l\u00e8ve\n\nNos chevaliers sont en cavale pour ramener le graal \u00e0 montr\u00e9al\nLe tournoi est un chemin de croix parsem\u00e9 d\u2019\u00e9moi\nMais la coupe, on y croit, comme autrefois, on a la foi\nPis si c\u2019est pas c\u2019t\u2019ann\u00e9e, ben comme dirait ren\u00e9\n\u00c0 la prochaine fois\nQu\u00e9b\u00e9cois !\n\nOn va\u2026\n\n[refrain]\n\nAllez Montr\u00e9al !\n\nDu sang neuf depuis 1909 avec\nJack laviolette, lach\nPitre et pit l\u00e9pine en passant par\nNewsy lalonde et joe malone\nAur\u00e8le et morenz\nHains\u2019, plante, gump et le concombre\nPocket rocket, boum boum, cournoyer, coco, carbo, casseau, naslund\n(oublie pas les anglos, yo)\nToe, dickie, doug et scotty\nShutt, larry, ken et bobby\nL\u2019arr\u00eat de roy, rebond, butch bouchard \u00e0 savard, vers b\u00e9liveau qui esquive un joueur\nPasse \u00e0 lafleur, lafleur acc\u00e9l\u00e8re, remet au rocket richard\nDeux hommes sur le dos, rien de trop gros\n\nEt le but !\n\nOn a gagn\u00e9, on a gagn\u00e9 !\nAllez Montr\u00e9al !\n\nOn veut gagner\nOn peut gagner\nOn va gagner !\n\nAllez Montr\u00e9al !", "image": "https://images.genius.com/3onfbpwfsh4rq85s5tsd1i8j0.550x550x1.jpg"}], "artist": "Loco Locass"}