{"songs": [{"title": "Gruau", "album": "Gullywood", "year": "2012-05-05", "lyrics": "[Verse 1: Loudmouth]\nAll about my paper so j'suis pas l\u00e0 si \u00e7a paye pas\nGruau international, as-sal\u00e2m 'ale\u00efkoum\nEnligne les cups sur le bar\nPop bottles, fais des d\u00e9g\u00e2ts\nFais la danse, lance tes bras\nGet lost, l\u00e2che l'\u00e9cole\nFait \u00e7a big (fait \u00e7a big)\nCuir Marc Jacobs\nBeat demande \u00e0 A-Just, uh, outrageous\nHipster-rich gr\u00e2ce \u00e0 CISM radio\nSo tu peux m'appeler Yann Payroll\nFuck that underground\nPas le temps pour tes conneries\nBitch dumb it down, les lobotomies sont on me\nOn est venu pour make it rain, boy tu penses qu'il pleut money\nLitt\u00e9ralement make it rain, boy t'attrapes un pneumonie\nAll gruau everything, fuck David Blaine\nLuc Langevin on the phone\nDis-y j'm'en viens r\u00e9gler des comptes\nAh-ah Loud and Lary depuis back in the days\nPis on va ride 'til we die, [???] in a day\n\n[Hook: Loudmouth]\nAll about my paper so j'suis pas l\u00e0 si \u00e7a paye pas\nGruau money all stars, met du fort dans mon Quaker\n\n[Verse 2: Lary Kidd]\nAll about my paper so j'suis pas l\u00e0 si \u00e7a paye pas, ah\n10 000 pour le party so c'est 20 000 pour le d\u00e9gat, ah\nPasse moi donc les Raybans pour le joint y faut des shades\nEt puis les jeunes idiotes du CEGEP full of gruau let me spray some, ah\nWilly Cartier-Bresson, longue lentille sur un Leica\nBaby fuck avec le boy, c'est le God, yeah c'est A-Just\nGruau money over everything tu savais d\u00e9j\u00e0\nC'est le bond de qualit\u00e9 de toute la gang de gruau Quaker\nT'appelles \u00e7a des avoirs baby moi j'appelle \u00e7a de l'avoine, yep\nAll about mes vieux hommes every day comme Eddie Savoie, yep\nSoleil!\nYou know I gotta get money\nQuand je joue d'la guit sur le sizzurp\nTu peux m'appeler Jeff Buckley\nKing, premi\u00e8re moisson\n\u00c7a fait \"Ting!\" sur le bracelet\nYeah on calculate le cream\nParce qu'on fiends sur la galette\nBaby fiend sur le sachet\nPrend une ligne de mon avoine\nTu va voir que c'est le thing badabing et puis voil\u00e0 okay\n\n[Hook]", "image": "https://images.genius.com/f18e293a54daf3f7752ea4cfa2b45fea.700x700x1.jpg"}], "artist": "Loud  Lary  Ajust"}