{"songs": [{"title": "Blue Volvo", "album": "Blue Volvo", "year": "2014-10-21", "lyrics": "[Verse 1 - Lary Kidd]\nYou wanna be a superstar baby\nBienvenue dans le nouvel \u00e2ge baby\nJ'nous vois tout de noir v\u00eatus\nDrop top 'train de faire les fous \u00e0 Las Vegas\nRun around sur le boulevard\nNaked sous le regard d\u00e9go\u00fbt\u00e9 des neighbors\nTu t'en souviens? Damn\nWe had a blast that night\nCops came over un tas d'plaintes du voisinage\nMon boy Gio avait la Volvo bleue\nOn \u00e9tait sept boys, so elle faisait la job pour deux\nOn chantait Kanye 808'\nMoi j'disais tout le temps qu'j'me compare \u00e0 Lil Wayne\nPis qu'le char \u00e9tait lou\u00e9, but it wasn't\nJ'me souviens des conneries\nJ'me souviens d'la fois o\u00f9 t'\u00e9tais pas l\u00e0\nPis la police est venue cogner \u00e0 la porte juste pour te pogner\nWas a close one\nYou saw me chuckin' up the deuces\nYeah je t'ai laiss\u00e9 tout seul, I regret it\n\n[Hook - Lary Kidd & Loud]\nToute mon adolescence j'ai vu la Blue Volvo spinnin' around and round\nPrenez place les amis sur les black leathers seats\nParce qu'on s'en va nulle part tonight\nY'a pas d'speed limit sur la Blue Volvo\nLes wheels keep spinnin' mais 'a tourne en rond\nLa ceinture autour du cou\nOn va rouler pour toujours, let's go\n\n[Verse 2 - Loud]\nStreet dreams d'in fen\u00eatres d'\u00e9cole\nT'as besoin d'dough then you sell dope, basic stuff\nIt gets tough though, le game c'est un sable mouvant\nUne fois que tu fais des revenus then you can never move on\nWhatever\nLe boy Gio avait la Blue Volvo\nLe Blueprint disait: \u00ab U Don't Know \u00bb\nSure we did not\nLittle did we know, we could get a lot\nMove a kilo on a d-low, make a killing as a dealer\nOn a toujours \u00e9t\u00e9 r\u00eaveurs since for ever\nDeux pieds sur le terre-plein, on pensait airplane\nSome big things to come\nYoung kings to crown\nNow we run things, that something to think about, uh\nL'ignorance \u00e9tait tellement wrong\nLa ligne orange semblait tellement longue\nWhen she was still around\nStill friends, no difference\nNothing but a nostalgie thang baby, uh\nJ'garde une couple de connexions \u00e0 Ahuntsic\nY'ont toujours les rem\u00e8des maisons quand j'feel home sick\nOn fait comme si, mais c'est p'us comme les premi\u00e8res fois\nMaintenant j'garde la t\u00eate froide devant la mauvaise foi\nUne coupe de fake friends disent qu'j'suis p'us really real\nSi j'avais fail, peut-\u00eatre qu'on pourrait relate\nMais l\u00e0 j'sais pas, man\nSome people that I grew up with just never grew up\nJ'ai pr\u00e9f\u00e9r\u00e9 les perdre de vue que d'les voir perdre, uh\n\n[Hook - Lary Kidd & Loud]\nToute mon adolescence j'ai vu la Blue Volvo spinnin' around and round\nPrenez place les amis sur les black leathers seats\nParce qu'on s'en va nulle part tonight\nY'a pas d'speed limit sur la Blue Volvo\nLes wheels keep spinnin' mais 'a tourne en rond\nLa ceinture autour du cou\nOn va rouler pour toujours, let's go\nToute mon adolescence j'ai vu la Blue Volvo spinnin' around and round\nPrenez place les amis sur les black leathers seats\nParce qu'on s'en va nulle part tonight\nY'a pas d'speed limit sur la Blue Volvo\nLes wheels keep spinnin' mais 'a tourne en rond\nLa ceinture autour du cou\nOn va rouler pour toujours, let's go", "image": "https://images.genius.com/f60e42202cecf9ac300636798f8cd19a.1000x1000x1.jpg"}], "artist": "Loud  Lary  Ajust"}