{"songs": [{"title": "Outro", "album": "Bonhomme Pendu (Chapitre 2)", "year": "2016-12-16", "lyrics": "C'est 3-0 n\u00e9gros j'tiens toujours les commandes\nCherche pas \u00e0 savoir le pourquoi du comment\nPourquoi du comment on r\u00e9colte s'que l'on s\u00e8me\nOn a l'fruit du d\u00e9mon\nTouche a la gang ou la moula\nOn fera couler l'sang comme si c'\u00e9tait du niania\nComme si c'\u00e9tait du niania on cachera ton cadavre dans le monde de Narnia\nJ'fais s'que j'dois faire pour sortir de la rue\nOn sera juger par dieu et non par la loi\nJ'connais bien les feuds apr\u00e8s tout s'que j'ai vue\nY'a personne qui m'fera croire que le client est roi\nLa v\u00e9rit\u00e9 blesse\nIls ont peur de la voir\nOn l'fera pour la ville quitte \u00e0 perdre la voix\nUn verre dans la main pour calmer ma folie\nJ'pr\u00e9f\u00e8re perdre le foie plut\u00f4t qu'perdre la foi\nEt tu sais qu'j'les rafales de janvier \u00e0  d\u00e9cembre\nDescend d'ton nuage ou j'viendrai t'faire descendre\nT'es pas l'parrain, on sait qu'tais l'middle man\nOn d\u00e9pose ton profit dans la pompe \u00e0 essence\nTu peux lire ma tristesse dans nos sourires\nOn a souffert de l'art dans des taudits\n? on pr\u00e9f\u00e9rerait mourrir\nBonhomme pendu si je tombe j'aurai ai tout dit\n\nJ'suis dans l'game pour prendre les sous\nJ'sais qu' le fame c'est chacun son tour\nJ'tais dans la merde ils \u00e9taient ou\nY peuvent pas m'hate le beat est lourd\n\nJ'suis dans l'game pour prendre les sous\nJ'sais qu' le fame c'est chacun son tour\nJ'tais dans la merde ils \u00e9taient ou\nY peuvent pas m'hate le beat est lourd", "image": "https://images.genius.com/3750697fcbaf3ab3a32bca2939053af9.640x640x1.jpg"}], "artist": "LOST [FR]"}