{"songs": [{"title": "P4 (LVMH Remix)", "album": "Bonhomme Pendu", "year": "2016-11-30", "lyrics": "[Intro]\nFree Dondon et free Bizon\nLost\n\n[Hook]\nN'oublie pas que la drogue est plus har\u0101m que rentable\n(N'oublie pas que la drogue est plus har\u0101m que rentable)\nOn d\u00e9balle, on mixe, on calcule et on remballe\n(On d\u00e9balle, on mixe, on calcule et on remballe)\n[?] dans l'sous-sol [?] sur le track\n([?] dans l'sous-sol [?] sur le track)\nUn refrain de quatre barres strat\u00e9giques, Kit-Kat\n(Un refrain de quatre barres strat\u00e9giques, Kit-Kat)\n\n[Verse 1]\n[?] t'aime pas\nTouche \u00e0 la famille, j'te d\u00e9coupe et j't'emballe\n\u00c0 deux heures tapantes, on est tous devant ta porte\nLa rafale va t'calmer si jamais tu t'emportes\nLe rap c'est Babylone, j'arrive et j'suis l'd\u00e9luge\nT'as rien fait dans la rue, mais t'es l\u00e0 d'puis des lunes\n[?] nique sa m\u00e8re la prison\nJ'ai du souhaiter bonne f\u00eate \u00e0 travers ma cellule\nJ'aime une femme qui m'rapproche de l'enfer \u00e0 petit feu\nLes petits m'adorent tous, j'ai peur qu'ils m'id\u00f4latrent\nJ't'un mauvais exemple, j'ai trop soif de dollars\n\u00c7a tire dans tous les sens, j'remercie le Tr\u00e8s-Haut\nAucune balle ne m'a tu\u00e9, j'ai l'chakra de N\u00e9o\nLe p\u00e8re No\u00ebl est mort et enterr\u00e9 depuis\n\u00c0 part d'\u00e7a personne donne de cadeaux gratuits\nY'a que des perroquets dans l'rap et j'en ai ras l'bec\nJ'fais des jambettes aux gens b\u00eates car la vie est injuste\nSi jamais j'me fais la Benz, c'est qu'j'ai pris une sale peine\nLe jeu n'en vaut pas la chandelle\nNique sa m\u00e8re le rap game\nFree Dondon et free Bizon\nOn a perdu des bonnes b\u00eates\n[?] les munitions, c'est qu'tu nous dois des longues dettes\nCousin, tu connais la suite\n[?] big up \u00e0 my nigga Tripp\nP.K. Subban on deck (P.K. Subban on deck)\nUne grosse [?] dans l'c\u0153ur, j'ai l'inspi d'un [?]\nJ'ai pris comme j'ai donn\u00e9\nPlus d'une [?] s'prennent tous pour des rois\nMais dans l'rap y'a pas d'king\nLe tr\u00f4ne n'est qu'une chaise, musicale\nLa nuit j'suis n\u00e9vros\u00e9\nMon cognac est dos\u00e9\nLe quartier c'est [?]\nFais gaffe, y pleut des [?], tu vas t'faire arroser\nQuand j'parle, y m'\u00e9coutent pas\nQu'est-ce tu m'parles de punchlines\nL'amour c't'une future gifle qui provient du revers de Serena Williams\nPour un p'tit bout d'papier, \u00e7a s'transforme en boureau\nJ'ai fait l'tour d'la question, j'suis au bout du rouleau\nUne liste remplie d'faux fr\u00e8res, le dos rempli d'couteaux\nLa confiance s'perd en litres et s'regagnent en [?]\nC'est normal que j'le tue, au niveau j'suis rendu\nSi j'trouve pas les bons mots, le bonhomme est pendu\nParole d'enfant perdu, l'atmosph\u00e8re est tendue\nLe daron m'parle m\u00eame plus\nJ'accumule la rancune\n\n[Hook]\nN'oublie pas que la drogue est plus har\u0101m que rentable\n(N'oublie pas que la drogue est plus har\u0101m que rentable)\nOn d\u00e9balle, on mixe, on calcule et on remballe\n(On d\u00e9balle, on mixe, on calcule et on remballe)\n[?] dans l'sous-sol [?] sur le track\n([?] dans l'sous-sol [?] sur le track)\nUn refrain de quatre barres strat\u00e9giques, Kit-Kat\n(Un refrain de quatre barres strat\u00e9giques, Kit-Kat)", "image": "https://images.genius.com/fdded08ba57388bb276d2586d8f21482.275x275x1.jpg"}], "artist": "LOST [FR]"}