{"songs": [{"title": "J'roule avec", "album": "CERB\u00c8RE", "year": "2017-07-25", "lyrics": "[Intro: JAROD]\nJ'roule avec, j'roule avec mon pote\nOn s'est fait la guerre mais c'est toujours mon pote\nY'a des hauts y'a des bas donc je vois la hess\nSi c'est ma gow fait attention \u00e0 c'que tu hep\nJ'me r\u00e9p\u00e8te, j'me r\u00e9p\u00e8te mon pote\nOn essaient d'briller avant qu'ils nous p\u00e8tent mon pote\nJ'voit les \u00e9toiles filantes, \u00e9toiles filantes\nJ'voit les \u00e9toiles filantes boy\n\n[Couplet 1: M.B]\nJ'ai pas l'temps \u00e0 perdre babe je doit m'en sortir\nTu sais que j'roule avec dit moi o\u00f9 est la sortie\nYeah, dit moi o\u00f9 est la sortie\nMon gars je dors plus la nuit, j'suis devenu un vampire\nJ'ai pas tourn\u00e9 ma veste non, non\nElle veut que je la ken mais moi je pense qu'\u00e0 mon oseille\nElle pense \u00e0 chaque moment\nChaque fois que je sors de la ville elle veut que j'roule avec\n\n[Refrain: JAROD et M.B]\nJ'roule avec les barres, barres de ma ville\nCh\u00e9rie j'sais qu'il est tard, j'ai pas l'air mais j'suis triste\nAppel comme m\u00eame, appel comme m\u00eame\nJ'fait mes bails, guerre depuis le bac \u00e0 sable\nJ'rentre ta senti la rafale\nDemande pas si \u00e7a va, demande pas si \u00e7a va\n\n[Couplet 2: JAROD]\nComment veut-tu aimer, ta jamais vu un homme\nIls cachent leur l\u00e2chet\u00e9 derri\u00e8re un gabarit de gorilles\nTu me verra mourir avant qu'ils m'nomment\nJ'suis un esp\u00e8ce rare, j'met un ?coup tu verra devoid?\nTu connais les bails, tu connais les bails\nAppel comme elle\nTu connais les bails, tu connais les bails\nAppel comme elle\n\n[Couplet 3: M.B]\nJ'ai du le faire malgr\u00e9 que j'ai perdu quelque ann\u00e9es\nTa vu mon fr\u00e8re au finale rien ne sert de parler\nTout mes fr\u00e8res sont arm\u00e9s\nYeah Yeah\nQuelque incomdan\u00e9\nJ'ai fait plus confiance au gens babe moi je m'en vais\nIls veulent r\u00e9gler mon compte, les jaloux sont mauvais\nYeah Yeah\nLes jaloux sont mauvais\nYeah Yeah\n\n[Refrain: JAROD et M.B]\nJ'roule avec les barres, barres de ma ville\nCh\u00e9rie j'sais qu'il est tard, j'ai pas l'air mais j'suis triste\nAppel comme m\u00eame, appel comme m\u00eame\nJ'fait mes bails, guerre depuis le bac \u00e0 sable\nJ'rentre ta senti la rafale\nDemande pas si \u00e7a va, demande pas si \u00e7a va\n\n[Couplet 4: JAROD]\nJ'monte au charbon tu veut mon pain on se fait la guerre\nJ'pourrais jamais assez d\u00e9dicacer ma m\u00e8re\nJ'roule avec elle, j'roule avec elle, j'roule avec elle\nFranchement j'ai pas d'nouveaux amis\n? d'la nuit\nYeah, il faut du cob pour la nuit\n\n[Refrain: JAROD et M.B]\nJ'roule avec les barres, barres de ma ville\nCh\u00e9rie j'sais qu'il est tard, j'ai pas l'air mais j'suis triste\nAppel comme m\u00eame, appel comme m\u00eame\nJ'fait mes bails, guerre depuis le bac \u00e0 sable\nJ'rentre ta senti la rafale\nDemande pas si \u00e7a va, demande pas si \u00e7a va\n\n[Outro: JAROD]\n75 MTL\nToute est bon\nM.B\nC'est toi qui avait raison\n??\nRappel comme m\u00eame enfoir\u00e9\nOn est l\u00e0 poto", "image": "https://images.genius.com/c89b4a873eb263d7738d4265e907280a.960x960x1.jpg"}], "artist": "M.B"}