{"songs": [{"title": "Waves", "album": null, "year": null, "lyrics": "(Heyyy)\n(Ok)\n\n[Refrain] x?\nExcuse moi pendant que j'touche le ciel\nDes fois j'ai l'impression que j'ai pas ma maternel\n[?] waves\nVive le system salaire on est pas des slaves\n\nYo Excuse moi pendant que j'touche le ciel\nJ'ai pas l'gout [?] comme les autres icitte\nVeux tu bouffer [?]\nAccrophone spas dead gang de po\u00e9tique (Non!)\nBack to work avec mon linge toute couvert de paint\n[?]de tes astronaute\nOn est spaced out comme des astronaute\nMercredi sur un turn up\nS't'allumer comme une torche olympique\nAu states y dise que c'est lit\n\nHello hello lady lady\nMoi pis elle sur un file\nMoi pis elle dans le lit\n9 mois apr\u00e8s gets real\nMoi plus elle dans l'lit\n9 mois apr\u00e8s gets real\n\nFallait penser [?]\nLa j'arrive de l'autre bord du soleil\nAvec un gros manque de sommeil\nHier jetais au sommet\nJ'ai dit au monde que j'les aimais\nAujourd'hui j'arrive sur terre sourire fendu jusqu'au oreilles\n\n[WIP]", "image": "https://images.genius.com/cd6d5e8e0190625cf5788fd8a5373e2c.706x706x1.jpg"}], "artist": "Eman x Vlooper"}