{"songs": [{"title": "Zaybae", "album": "La Zayt\u00e9", "year": "2018-07-13", "lyrics": "(Yeah)\n\n[Refrain]\nZaybae\nT'es ma Zaybae\nZaybae\nOuuuh, t'es ma Zaybae\nZaybae\nT'es ma Zaybae\nOuuuh, Zaybae\nYeah, t'es ma Zaybae\n\nFais toi pas finesse pour une paire de fesses\nJ'ai la Zaybae, y'a pas de prospect\nFirst pick, overall number one, yeah\nLes gars courent apr\u00e8s, c\u2019est moi qui home run yeah\nMan, sont mieux d\u2019courir vite\nWinner, j'ai z\u00e9ro limite, yeah\nYeah, sont mieux d\u2019travailler fort\nJuste des bonnes raisons si tu veilles tard, yeah\n\nMan elle collection les passes d\u2019artiste\nNext step, je l\u2019emm\u00e8ne \u00e0 l\u2019ADISQ\nTout le squad sur le mari kush\nDoc Martens sur le tapis rouge\nBelle boucle d\u2019oreille, elle met le makeup\nQui l\u2019aurait cru, man, on a make it\nShe is a thug, c'pu un enfant\nDes fois, elle met d'la blow dans son Kankan\n\nSmoking all day\nLa journ\u00e9e longue\nFeeling all zay\nL\u2019amour est stone\nYeah, elle aime \u00eatre high quand on konyin\nAfter burn, bien allong\u00e9\nLe soleil se l\u00e8ve\nElle part \u00e0 job\nLe soleil se couche\nJust wake up\nElle prend une couple de selfie sur mon t\u00e9l\u00e9phone\nM\u2019r\u00e9veille avec des becs, \u00e7a lui fait du fun\n\nTout son chakra dans un bisou sur ma joue\nElle enl\u00e8ve ses v\u00eatements, c\u2019est son sexy jutsu\nElle d\u00e9cide comment on s\u2019habille \u00e0 mon show\nYeah, Beachclub, avec ma gang de manchots\nTemps qu\u2019on est heureux, on n'a pas besoin d'bl\u00e9\nOn doit rien \u00e0 personne, viens qu\u2019on parte away\nL\u2019amour, c\u2019est venimeux, j'veux pas arr\u00eater\nC'est ma rigoleuse, c\u2019est ma Zaybae\n\n[Refrain]\nZaybae (Yeah)\nT'es ma Zaybae (Yeah)\nZaybae (Yeah)\nOuuuh, t'es ma Zaybae  (Yeah)\nZaybae (ouh)\nT'es ma Zaybae (yeah)\nOuuuh, Zaybae\nYeah, t'es ma Zaybae\n\n(Le Michel Silencieux)", "image": "https://images.genius.com/167e448a5f4cc0a67ecdd0fd0369931b.1000x1000x1.jpg"}], "artist": "FouKi"}